Workbook

Sheet SEGUIMIENTO COMPRAS TRIBE
A1: STOCK | B1: CLIENTE | C1: ITEM | D1: CANTIDAD | E1: LINK DE COMPRA | F1: VALOR PRESUPUESTADO | G1: FECHA DE COMPRA | H1: VALOR DE COMPRA | I1: VALOR DEBITADO | J1: TAX 4% | K1: COSTO ENVIO | L1: PESO | M1: ITEM STATUS | N1: SALDADO | O1: ASIGNADO | P1: GANANCIA | Q1: SALDADO A ? | R1: ✅ 🇺🇸 💵 | S1: TRACKING | T1: OBSERVACIONES
A2: NO | B2: abel | C2: CHAPON WRX | D2: 1 | E2: https://www.amazon.com/gp/product/B00PV6T5U4/ref=ppx_yo_dt_b_asin_title_o03_s00?ie=UTF8&psc=1 | F2: 600 | G2: 45009 | H2: 183.51 | I2: 185.35 | J2: =I2+(I2*0.04) -> 192.764 | K2: 160 | M2: DONE | N2: SI | P2: =F2-(J2+K2) -> 247.236 | R2: SI | S2: UPS: 1ZVE87110302402577 | T2: ENTREGADO A CLIENTE
A3: NO | B3: abel | C3: GUARDAPLAST WRX | D3: 1 | E3: https://www.ebay.com/itm/371496693838 | F3: 210 | G3: 45014 | H3: 32.2 | I3: 32.52 | J3: =I3+(I3*0.04) -> 33.8208 | K3: 40 | M3: DONE | N3: SI | P3: =F3-(J3+K3) -> 136.1792 | R3: SI | S3: FedEx: 396389639118 | T3: ENTREGADO A CLIENTE
A4: NO | B4: yani | C4: BOMBA WALBRO | D4: 1 | F4: 265 | H4: 158.9 | I4: 160.49 | J4: =I4+(I4*0.04) -> 166.9096 | K4: 40 | M4: DONE | N4: SI | P4: =F4-(J4+K4) -> 58.0904 | R4: SI | S4: TBA305962486126 | T4: ENTREGADO A CLIENTE
A5: NO | B5: alfredo si | C5: PASTILLAS HAWK | D5: 1 | F5: 55 | I5: 0 | J5: 0 | K5: 40 | M5: DONE | N5: SI | P5: =F5-(J5+K5) -> 15 | R5: SI | S5: FedEx: 396305659584 | T5: ENTREGADO A CLIENTE
A6: NO | B6: NERF | C6: TECLADO | D6: 1 | F6: 0 | J6: =I6+(I6*0.04) -> 0 | K6: 0 | M6: DONE | N6: SI | P6: =F6-(J6+K6) -> 0 | R6: SI | S6: UPS: 1ZA533G60318105439 | T6: ENTREGADO A CLIENTE
A7: NO | B7: abel | C7: PASARUEDAS WRX | D7: 1 | E7: https://www.amazon.com/gp/product/B07F1C9MFJ/ref=ppx_yo_dt_b_asin_title_o04_s00?ie=UTF8&psc=1 | F7: 90 | G7: 45009 | H7: 42.75 | I7: 43.18 | J7: =I7+(I7*0.04) -> 44.9072 | K7: 40 | M7: DONE | N7: SI | P7: =F7-(J7+K7) -> 5.0928 | R7: SI | S7: FEDEX: 396202387161 | T7: ENTREGADO A CLIENTE
A8: NO | B8: Migale | C8: OPTICA VOLVO DER | D8: 1 | E8: https://www.ebay.com/itm/175564026454?hash=item28e06e7256:g:JvoAAOSw-7Zj5CHH&amdata=enc%3AAQAHAAAAoIXUlg1UNk7TbYe3FabkWPJcOXfJjxUdU08uXWu1bYnwPC%2F23lQcUalfPDXA%2F0bT7Dz8P784RjZYuWHUWf3%2FRm9HK5lbZH%2Bpvp4UpWfQ6acBIQlrqP6gYfBB82zF0Jk0tSlwsMADKQudHIX1zkphqSG%2Fu1alGJE6zwIH1wHmaGDwTtkRuLmMbjumRFo4AXXWtp2rXLDnyNCurdnkhCTrurY%3D%7Ctkp%3ABk9SR_zgqLTJYQ | F8: 900 | H8: 426.91 | I8: 431.18 | J8: =I8+(I8*0.04) -> 448.4272 | K8: 225 | M8: DONE | N8: SI | P8: =F8-(J8+K8) -> 226.5728 | R8: SI | S8: FedEx: 396575849146 | T8: ENTREGADO A CLIENTE
A9: NO | B9: Migale | C9: OPTICA VOLVO IZQ | D9: 1 | E9: https://www.ebay.com/itm/404223900795?hash=item5e1d9f3c7b:g:5YgAAOSwMyhkJdSM&amdata=enc%3AAQAHAAAA8FSz39KtRB%2BPktdf2yt1G8hS8rRdtTIp4RLsIvLQuULpWtmk1v90Xi%2FEB4ii2lYGvs4cGUkO0HRK1lPAO34hmV5OUoiPnYQLJaqewa5lB3ZXz%2BhmsKNyhZof4IQJ%2FWv2xlZ9%2FWl5gnqKO0b4IM33c0zK7dT9oujExAc9Tv1tzcbmEXvX9Xrs%2Fenczwd4vz7Hi2yd7LarkyqKUoxuYSG8zCrePPHOhp7eqdQHkdlHV5%2Fn6p%2Bl2ARvfPH%2Bg8iwAahZZHXBXDJeBp7JoQdLCTWllwssyhqo%2BTb3OSANMyao9ed%2FYIVMVquVrL3lfOb0UeEmmQ%3D%3D%7Ctkp%3ABk9SR47u8L3mYQ | F9: 720 | H9: 293.08 | I9: 296.01 | J9: =I9+(I9*0.04) -> 307.8504 | K9: 225 | M9: DONE | N9: SI | P9: =F9-(J9+K9) -> 187.1496 | R9: SI | S9: FedEx: 396465905948 | T9: ENTREGADO A CLIENTE
A10: NO | B10: Migale | C10: COVER VOLVO | D10: 1 | E10: https://www.ebay.com/itm/114182300635?epid=1825189926&hash=item1a95cba3db:g:dFoAAOSwWPtekcc9&amdata=enc%3AAQAHAAAA4JrdX9uEUhHyuVzc44752o8kG3lPhqEEx2lIvydvC4uYRyeK6WB8RMwkC%2Fx9qt50tLZSrVnQuH7AAsw%2BLfIJLxIPI9wDizaFB4OCCy8O46qP55QL9PHz6ikjO3v7lzenqPwNffIxxPZ98wa8KZok%2FfsR%2FTUlGu4CcWlA8YqX4ppIAhBxdqHDcHCLTRidFUObqkATtLCoek1IU6%2Bx8%2FlDry82UYsjVdxHcrTRBsNuibxu8W602dHpFgjPVHIiBDyXjBY1XvmfgXdDk5KH0U8hIobC3Ak2XpBA3NhYekhhHvPg%7Ctkp%3ABk9SR_L4zLzmYQ | F10: 260 | G10: 45016 | H10: 87.12 | I10: 87.99 | J10: =I10+(I10*0.04) -> 91.5096 | K10: 80 | M10: DONE | N10: SI | P10: =F10-(J10+K10) -> 88.4904 | R10: SI | S10: FedEx:642099607710 | T10: ENTREGADO A CLIENTE
A11: NO | B11: Migale | C11: PARTS VOLVO | D11: 1 | E11: https://www.volvocarsoempartsdirect.com/checkout/aaa827035d449822ff600c6a73a71e65/shipping | F11: 2270 | H11: 1064.31 | I11: 1064.31 | J11: =I11+(I11*0.04) -> 1106.8824 | K11: 525 | M11: DONE | N11: SI | P11: =F11-(J11+K11) -> 638.1176 | R11: SI | S11: oldominion: 07114388254 | T11: ENTREGADO A CLIENTE
A12: NO | B12: Migale | C12: INTERFAZ VOLVO | D12: 1 | E12: https://www.amazon.com/-/es/Davitu-CarPlay-corriente-cable-5G0035222E/dp/B07M9RL1GD | F12: 150 | H12: 110.01 | I12: 111.11 | J12: =I12+(I12*0.04) -> 115.5544 | K12: 13 | M12: DONE | N12: SI | P12: =F12-(J12+K12) -> 21.4456 | R12: SI | S12: I sent you something from Amazon. You can track the delivery with this link. https://a.co/d/0h0HmIc | T12: ENTREGADO A CLIENTE
A13: NO | B13: Juan Rosso | C13: AKRAPOVIC | D13: 1 | E13: https://www.ebay.com/itm/115099474123 | F13: 0 | I13: 0 | J13: =I13+(I13*0.04) -> 0 | K13: 120 | M13: DONE | N13: SI | P13: =F13-(J13+K13) -> -120 | R13: SI | S13: DHL:5951504053 | T13: ENTREGADO A CLIENTE
A14: NO | B14: Axel Margossian | C14: Repuestos monopatin | D14: 1 | E14: n/a | F14: 220 | H14: 0 | I14: 0 | J14: =I14+(I14*0.04) -> 0 | K14: 180 | M14: DONE | N14: SI | P14: =F14-(J14+K14) -> 40 | R14: SI | S14: Fedex: 396683414634 | T14: ENTREGADO A CLIENTE
A15: NO | B15: Alan Olmedo | C15: Paragolpe M3 | D15: 1 | E15: https://www.ecstuning.com/b-ecs-parts/m3-replica-bumper-kit-non-integrated-lip/bm51009akt/ | F15: 1100 | G15: 45026 | H15: 368.98 | I15: 372.67 | J15: =I15+(I15*0.04) -> 387.5768 | K15: 480 | M15: DONE | N15: SI | P15: =F15-(J15+K15) -> 232.4232 | R15: SI | S15: Fedex: 466153718655061 | T15: ENTREGADO A CLIENTE
A16: NO | B16: Abel | C16: GFB Diverter T9356 | D16: 1 | E16: ebay | F16: 295 | H16: 117.7 | I16: 118.88 | J16: =I16+(I16*0.04) -> 123.6352 | K16: 30 | M16: DONE | N16: SI | P16: =F16-(J16+K16) -> 141.3648 | R16: SI | S16: USPS: 9400136106089681321152 | T16: ENTREGADO A CLIENTE
A17: NO | B17: Abel | C17: Filtro | D17: 1 | E17: https://www.ecstuning.com/b-afe-parts/pro-dry-s-air-filter/31-10226~afe/ | F17: 225 | H17: 105.41 | I17: 106.46 | J17: =I17+(I17*0.04) -> 110.7184 | K17: 40 | M17: DONE | N17: SI | P17: =F17-(J17+K17) -> 74.2816 | R17: SI | S17: Ups: 1Z404524YW90966922 | T17: ENTREGADO A CLIENTE
A18: NO | B18: Abel | C18: Pure turbo | D18: 1 | E18: https://www.pureturbos.com/product/bmw-n55-pure-stage-2/?attribute_pa_wastegateactuatortype=8a-electronicewg&attribute_pa_coredeposit-mustmatchturboyou=7b-ewgcore&attribute_pa_divertervalveupgrade=f2-no&attribute_pa_installationkit=f2-no&attribute_pa_highflowinlet=0f-f-seriesoption2 | F18: 5924 | H18: 3560 | I18: 3595.6 | J18: =I18+(I18*0.04) -> 3739.424 | K18: 640 | M18: DONE | N18: SI | P18: =F18-(J18+K18) -> 1544.576 | R18: SI | S18: UPS: 1ZWA81613597112914 | T18: ENTREGADO A CLIENTE
A19: NO | B19: Abel | C19: VRSF INTERCOOLER & CHARGE & OUTLET | D19: 1 | E19: https://www.vr-speed.com/checkout/order-received/100314774/?key=wc_order_7mfTX1ByiMW65&utm_nooverride=1 | F19: 2375 | G19: 45028 | H19: 778.97 | I19: 780 | J19: =I19+(I19*0.04) -> 811.2 | K19: 745 | M19: DONE | N19: SI | P19: =F19-(J19+K19) -> 818.8 | R19: SI | S19: fedex: 396974811467 | T19: ENTREGADO A CLIENTE
A20: NO | B20: Yani | C20: sensor Burger | D20: 1 | E20: https://burgertuning.com/products/jb4-3-5-bar-tmap-adapter?variant=2104148885528 | F20: 160 | G20: 45030 | H20: 107 | I20: 108.07 | J20: =I20+(I20*0.04) -> 112.3928 | K20: 13 | M20: DONE | N20: SI | P20: =F20-(J20+K20) -> 34.6072 | R20: SI | S20: usps: 9400111206214130779369 | T20: ENTREGADO A CLIENTE
A21: NO | B21: Abel | C21: Llantas M2 | D21: T | E21: https://www.getbmwparts.com/oem-parts/bmw-m-performance-frozen-gold-19-quot-style-763m-rim-9jx19-et-29-36118097287 | F21: 10120 | G21: 45029 | H21: 5103 | I21: 5154.68 | J21: =I21+(I21*0.04) -> 5360.8672 | K21: 2200 | M21: DONE | N21: SI | P21: =F21-(J21+K21) -> 2559.1328 | R21: SI | S21: UPS: 1Z283637A895717838 UPS: 1Z283637A898707647 / UPS: 1Z283637A895717838 UPS: 1Z283637A898707647 | T21: ENTREGADO A CLIENTE
A22: NO | B22: Abel | C22: Dorch Stage 2 | D22: 1 | E22: https://dorchengineering.com/checkout/order-received/3789?key=wc_order_sjD8AdGJvJLAb | F22: 2600 | G22: 45034 | H22: 1710.93 | I22: 1728.04 | J22: =I22+(I22*0.04) -> 1797.1616 | K22: 120 | M22: DONE | N22: SI | P22: =F22-(J22+K22) -> 682.8384 | R22: SI | S22: https://www.trackmyshipment.co/shipment-tracking/ESUS140777492 | T22: ENTREGADO A CLIENTE
A23: NO | B23: Mili mouso | C23: Bad bunny 7.5 us | D23: 1 | E23: https://www.goat.com/ | F23: 418 | G23: 45035 | H23: 261.62 | I23: 264.24 | J23: =I23+(I23*0.04) -> 274.8096 | K23: 100 | M23: DONE | N23: SI | P23: =F23-(J23+K23) -> 43.1904 | R23: SI | S23: https://track.parxl.com/PXLMY00323D02PU1 | T23: ENTREGADO A CLIENTE
A24: NO | B24: Abel | C24: Side Grill Trims | D24: 1 | E24: https://order.ebay.com/ord/show?/ViewPaymentStatus&purchaseOrderId=13-0996-606294#/ | F24: 422 | G24: 45036 | H24: 107 | I24: 108.07 | J24: =I24+(I24*0.04) -> 112.3928 | K24: 10 | M24: DONE | N24: SI | P24: =F24-(J24+K24) -> 299.6072 | R24: SI | S24: Latvia Post: RR917399666LV | T24: ENTREGADO A CLIENTE
A25: NO | B25: sergio | C25: Downpipe 240 g42 | D25: 1 | F25: 0 | G25: 45036 | H25: 390.99 | I25: 398.03 | J25: =I25+(I25*0.04) -> 413.9512 | K25: 0 | M25: DONE | N25: SI | P25: =F25-(J25+K25) -> -413.9512 | R25: SI | S25: https://trackshipment.shipstation.com/?branding_id=001d6731-0000-0000-1ebf-030000000000&carrier_code=ups&tracking_number=1ZA83W70DG25025584&order_number=MjI4Mzk4&postal_code=33166-2783&locale=en | T25: ENTREGADO A CLIENTE
A26: NO | B26: Rodri Freijedo | C26: Modulo encendido Honda | D26: 5 | E26: https://www.ebay.com/itm/134478644829 | F26: 605 | G26: 45040 | H26: 202.05 | I26: 218.35 | J26: 0 | K26: 40 | M26: DONE | N26: SI | P26: =F26-(J26+K26) -> 565 | R26: SI | S26: SpeedPAK: ES10023171321710001010001C0N | T26: ENTREGADO A CLIENTE
A27: NO | B27: Rodri Freijedo | C27: IACV Honda | D27: 5 | E27: https://www.ebay.com/itm/394507131153 | G27: 45040 | H27: 107.45 | I27: 118.48 | J27: 0 | K27: 20 | M27: DONE | N27: SI | P27: =F27-(J27+K27) -> -20 | R27: SI | S27: USPS: 9205590338269300665575 | T27: ENTREGADO A CLIENTE
A28: NO | B28: Rodri Freijedo | C28: CPK Sensor Honda | D28: 5 | E28: https://www.ebay.com/itm/191369133571 | G28: 45040 | H28: 74.6 | I28: 68.52 | J28: 0 | K28: 13 | M28: DONE | N28: SI | P28: =F28-(J28+K28) -> -13 | R28: SI | S28: FedEx: 397477801104 | T28: ENTREGADO A CLIENTE
A29: NO | B29: Abel | C29: BMW M2 1:18 | D29: 1 | E29: https://order.ebay.com/ord/show?orderId=10-09967-16454#/ | F29: 0 | H29: 172.37 | I29: 174.09 | J29: =I29+(I29*0.04) -> 181.0536 | K29: 100 | M29: DONE | N29: SI | P29: =F29-(J29+K29) -> -281.0536 | R29: SI | S29: Poste Italiane: RC179421742IT | T29: ENTREGADO A CLIENTE
A30: NO | B30: Abel | C30: Carbon fiber Mirrors & Exhaust tips | D30: 1 | E30: https://ind-distribution.com/6762364997/orders/8f77180929762682c4a74bab5cbbd6a8 | F30: 1199 | G30: 45042 | H30: 814.11 | I30: 822.25 | J30: =I30+(I30*0.04) -> 855.14 | K30: 200 | M30: DONE | N30: SI | P30: =F30-(J30+K30) -> 143.86 | R30: SI | S30: UPS: 1Z57Y1080371048015 - UPS: 1Z57Y1084270735380 (MIRRORS) | T30: ENTREGADO A CLIENTE
A31: NO | B31: Abel | C31: Riñones | D31: 1 | E31: https://autotecknic.com/26746278/orders/37b1e11fb56e0775086af1f0a7c31b51 | F31: 269 | G31: 45042 | H31: 171.48 | I31: 173.19 | J31: =I31+(I31*0.04) -> 180.1176 | K31: 40 | M31: DONE | N31: SI | P31: =F31-(J31+K31) -> 48.8824 | R31: SI | S31: UPS: 1Z8A34840317299430 | T31: ENTREGADO A CLIENTE
A32: NO | B32: Abel | C32: Capot CS | D32: 1 | E32: https://www.paypal.com/invoice/s/pay/INV2-ZPJ3-UVUH-2EG6-UPVY?v=1&utm_source=unp&utm_medium=email&utm_campaign=RT000426&utm_unptid=c884f738-df95-11ed-b2f8-3cecef47c1cd&ppid=RT000426&cnac=AR&rsta=en_US%28en-AR%29&cust=4JFB9WGZWMDB4&unptid=c884f738-df95-11ed-b2f8-3cecef47c1cd&calc=f392033bca259&unp_tpcid=invoice-buyer-payment-notification&page=main%3Aemail%3ART000426&pgrp=main%3Aemail&e=cl&mchn=em&s=ci&mail=sys&appVersion=1.161.0&xt=104038 | F32: 3050 | G32: 45036 | H32: 1352 | I32: 1352 | J32: =I32+(I32*0.04) -> 1406.08 | K32: 1470 | M32: DONE | N32: SI | P32: =F32-(J32+K32) -> 173.92 | R32: SI | S32: road runner: 611707217 | T32: ENTREGADO A CLIENTE
A33: NO | B33: Abel | C33: Aleron | D33: 1 | E33: https://www.aeroluxeautoboutique.com/commerce/orders/578a2dfb-2904-4c28-b500-4e3383b05d26 | F33: 789 | G33: 45042 | H33: 370 | I33: 370 | J33: =I33+(I33*0.04) -> 384.8 | K33: 120 | M33: DONE | N33: SI | P33: =F33-(J33+K33) -> 284.2 | R33: SI | S33: Fedex: 772013125060 | T33: ENTREGADO A CLIENTE
A34: NO | B34: Juan Papa | C34: ORDEN 1 Grande Repuestos M4 | D34: 1 | E34: https://www.getbmwparts.com/account/order?token=eyJ0eXAiOiJKV1QiLCJhbGciOiJIUzUxMiJ9.eyJvcmRlcl9udW1iZXIiOiI0NDEyMjcxOCIsInVzZXJfZW1haWwiOiJlbWlsaWFub0B0cmliZXNoaXBwaW5nLmNvbSJ9.csmHHYhXDjb5MDbQsrU24X0QXKD8eydtcXhM_Eh8qgvH0KQ7MChNrWSndrBee9w_UdEEiPd3K0-xjb3CgtDerA | F34: https://docs.google.com/spreadsheets/d/1krhqWKlIKFe6dnrTzcq6TyNLydmBDFXhPjvPEzYNR8M/edit#gid=0 | G34: 45041 | H34: 6350.33 | I34: 6413.83 | J34: =I34+(I34*0.04) -> 6670.3832 | K34: 2815 | M34: DONE | N34: SI | P34: =F34-(J34+K34) -> #VALUE! | R34: SI | S34: UPS: 089957302 | T34: ENTREGADO A CLIENTE
A35: NO | B35: Juan Papa | C35: ORDEN 2 Grande Repuestos M4 | D35: 1 | E35: https://www.getbmwparts.com/account/order?token=eyJ0eXAiOiJKV1QiLCJhbGciOiJIUzUxMiJ9.eyJvcmRlcl9udW1iZXIiOiI0NDEyMjcyMCIsInVzZXJfZW1haWwiOiJlbWlsaWFub0B0cmliZXNoaXBwaW5nLmNvbSJ9.4LQ2CZE8zPJLyim14VsFbs0Sv7FZRFfeKc6_tn86JplyrWAWbfMJXpThiPKXEUq7MnArZlptOShvECs24MQVbw | F35: https://docs.google.com/spreadsheets/d/1krhqWKlIKFe6dnrTzcq6TyNLydmBDFXhPjvPEzYNR8M/edit#gid=0 | G35: 45041 | H35: 829.83 | I35: 838.13 | J35: =I35+(I35*0.04) -> 871.6552 | K35: 360 | M35: DONE | N35: SI | P35: =F35-(J35+K35) -> #VALUE! | R35: SI | S35: UPS: 1ZCF3305A818812337 | T35: ENTREGADO A CLIENTE
A36: NO | B36: NERF | C36: Cepillos detail | D36: 1 | E36: amazon | F36: 0 | I36: 0 | J36: =I36+(I36*0.04) -> 0 | K36: 0 | M36: DONE | N36: SI | P36: =F36-(J36+K36) -> 0 | R36: SI | S36: https://www.amazon.com/progress-tracker/package/ref=ppx_yo_dt_b_track_package?_encoding=UTF8&itemId=pnnirskokptoqn&orderId=111-5981075-1761066&packageIndex=0&shipmentId=MhhrVvplf&vt=YOUR_ORDERS | T36: ENTREGADO A CLIENTE
A37: NO | B37: Tano | C37: Switch Mazda | D37: 1 | E37: https://www.amazon.com/gp/product/B09FSSTD34/ref=ppx_yo_dt_b_asin_title_o01_s00?ie=UTF8&psc=1 | F37: 100 | G37: 45040 | H37: 38.25 | I37: 38.63 | J37: =I37+(I37*0.04) -> 40.1752 | K37: 0 | M37: DONE | N37: SI | P37: =F37-(J37+K37) -> 59.8248 | R37: SI | S37: https://www.amazon.com/progress-tracker/package/ref=ppx_yo_dt_b_track_package?_encoding=UTF8&itemId=pmslpqhlrrkwqn&orderId=111-7212672-1937055&packageIndex=0&shipmentId=Dv3mBRNG7&vt=YOUR_ORDERS | T37: ENTREGADO A CLIENTE
A38: NO | B38: Alan Olmedo | C38: Intercooler VRSF | D38: 1 | E38: https://www.vr-speed.com/vrsf-intercooler-fmic-upgrade-kit-12-16-f20-f30-228i-m235i-328i-335i-428i-435i-n20-n55.html | F38: 1150 | G38: 45052 | H38: 379.99 | I38: 383.79 | J38: =I38+(I38*0.04) -> 399.1416 | K38: 495 | M38: DONE | N38: SI | P38: =F38-(J38+K38) -> 255.8584 | R38: SI | S38: Fedex: 398020036489 | T38: ENTREGADO A CLIENTE
A39: NO | B39: Alan Olmedo | C39: Filtro ECS | D39: 1 | E39: https://www.ecstuning.com/Cart/Receipt-652996050/?customerID=2679329 | F39: 90 | G39: 45054 | H39: 35.81 | I39: 36.17 | J39: =I39+(I39*0.04) -> 37.6168 | K39: 40 | M39: DONE | N39: SI | P39: =F39-(J39+K39) -> 12.3832 | R39: SI | S39: Ups: 1Z404524YW99159663 | T39: ENTREGADO A CLIENTE
A40: NO | B40: Anibal Bento | C40: Sensor de fase land rover | D40: 1 | E40: https://www.roverparts.com/cart/receipt.cfm?id=5187696&uuid=BF3D1404-4416-49AF-892352589BCF5921 | F40: 335 | G40: 45054 | H40: 203.9 | I40: 205.94 | J40: =I40+(I40*0.04) -> 214.1776 | K40: 0 | M40: DONE | N40: SI | P40: =F40-(J40+K40) -> 120.8224 | R40: SI | S40: Usps: 9400116902200601765773 | T40: ENTREGADO A CLIENTE
A41: NO | B41: Juan Papa | C41: Ropa | D41: 1 | J41: =I41+(I41*0.04) -> 0 | K41: 225 | M41: DONE | N41: SI | P41: =F41-(J41+K41) -> -225 | R41: SI | S41: DHL: X2 | T41: ENTREGADO A CLIENTE
A42: NO | B42: Axel Margossian | C42: Repuestos camaro | D42: 1 | F42: 220 | H42: 0 | I42: 0 | J42: =I42+(I42*0.04) -> 0 | K42: 155 | M42: DONE | N42: SI | P42: =F42-(J42+K42) -> 65 | R42: SI | S42: UPS | T42: ENTREGADO A CLIENTE
A43: NO | B43: Alan Olmedo | C43: Discos traseros M3 E36 | D43: 1 | E43: https://www.ecstuning.com/MyAccount/Orders/Order-843805450/ | F43: 1157 | G43: 45061 | H43: 208.99 | I43: 211.08 | J43: =I43+(I43*0.04) -> 219.5232 | K43: 630 | M43: DONE | N43: SI | P43: =F43-(J43+K43) -> 307.4768 | R43: SI | S43: Fedex: 602607717461 | T43: ENTREGADO A CLIENTE
A44: NO | B44: Alan Olmedo | C44: Pastillas traseras & sensor | D44: 1 | E44: https://www.ecstuning.com/MyAccount/Orders/Order-195283626/ | G44: 45061 | H44: 116.47 | I44: 117.63 | J44: =I44+(I44*0.04) -> 122.3352 | K44: 90 | M44: DONE | N44: SI | P44: =F44-(J44+K44) -> -212.3352 | R44: SI | S44: Ups: 1Z404524YW96708511 | T44: ENTREGADO A CLIENTE
A45: NO | B45: Alan Olmedo | C45: Flange agua M3 | D45: 1 | E45: https://www.bmwpartsdeal.com/online/order/status?orderNumber=CB17237487&email=arraydude%40gmail.com | F45: 70 | G45: 45065 | H45: 31.72 | I45: 32.04 | J45: =I45+(I45*0.04) -> 33.3216 | K45: 0 | M45: DONE | N45: SI | P45: =F45-(J45+K45) -> 36.6784 | R45: SI | S45: USPS: 9405511206364860656751 | T45: ENTREGADO A CLIENTE
A46: NO | B46: Hector Mercedes | C46: Techo mercedes | D46: 1 | E46: https://order.ebay.com/ord/show?itemId=354072826792&transactionId=1430849518022&mkevt=1&mkpid=0&emsid=e11401.m1842.l5919&mkcid=7&ch=osgood&euid=615f5ab7ca6845a98239bdea3121b3c4&bu=43795160990&exe=0&ext=0&osub=-1%7E1&crd=20230522034054&segname=11401#/ | F46: 240 | G46: 45065 | H46: 101.65 | I46: 102.67 | J46: =I46+(I46*0.04) -> 106.7768 | K46: 90 | M46: DONE | N46: SI | P46: =F46-(J46+K46) -> 43.2232 | R46: SI | S46: FedEx: 772208858778 | T46: ENTREGADO A CLIENTE
A47: NO | B47: Alan Olmedo | C47: Riñones 335 | D47: 1 | E47: https://www.ebay.com/itm/185726941194?fits=Make%3ABMW&hash=item2b3e30380a:g:Ek4AAOSwpstjt754&amdata=enc%3AAQAIAAAA0MVXu0UK3E%2FCTXKAHSy8VL8TueYAbyDu%2FV1k2QkTlwP767elk2MBw8PvY3v%2B2MKozJmO150FWRqKGADsUtrokiSMyTy0iVpaibEPP64NucxoqnLXw992CmTw9ow%2FnGDpCrf2nOpxRv5tKpfKzQJNoy2D3VrRfNDF42S2SK67rZjwT4LBSQbYWsXmlOAhwLGgKPPvWOFTixTY26D8%2BcmcGgpuPrIxxYBEyJ14UspDddefqa2Awdn8Y2OB2cB%2B0okEOBh7tMvX8u3%2BDC9tCYbYIPo%3D%7Ctkp%3ABk9SR4KS6sOIYg | F47: 120 | G47: 45068 | H47: 50.81 | I47: 51.32 | J47: =I47+(I47*0.04) -> 53.3728 | K47: 40 | M47: DONE | N47: SI | P47: =F47-(J47+K47) -> 26.6272 | R47: SI | S47: China Post: LR050011125CN | T47: ENTREGADO A CLIENTE
A48: NO | B48: Demian | C48: Ducha | D48: 1 | E48: https://www.boelon.com/checkouts/c/8048b1285556474d9b0d6b1872375a4e/thank_you | F48: 899 | G48: 45070 | H48: 449 | I48: 457.08 | J48: =I48+(I48*0.04) -> 475.3632 | K48: 280 | M48: DONE | N48: SI | P48: =F48-(J48+K48) -> 143.6368 | R48: SI | S48: DHL: 4601426406 | T48: ENTREGADO A CLIENTE
A49: NO | B49: Emiliano Righetti | C49: Radiador bmw | D49: 1 | E49: https://www.ebay.com/itm/153972028238?_ul=AR | F49: 720 | G49: 45076 | H49: 224.89 | I49: 227.14 | J49: =I49+(I49*0.04) -> 236.2256 | K49: 270 | M49: DONE | N49: SI | P49: =F49-(J49+K49) -> 213.7744 | R49: SI | S49: UPS: 1Z7A377E0393770627 | T49: ENTREGADO A CLIENTE
A50: NO | B50: Juan Papa | C50: Guardaplast | D50: 1 | E50: https://www.bmwpartsdeal.com/online/order/summary?orderId=232250&orderGuid=1bf5b7d7-2099-4762-be14-536dc495e96c | F50: 0 | G50: 45076 | H50: 135.14 | I50: 136.49 | J50: =I50+(I50*0.04) -> 141.9496 | K50: 80 | M50: DONE | N50: SI | P50: =F50-(J50+K50) -> -221.9496 | R50: SI | S50: Fedex: 399069149250 | T50: ENTREGADO A CLIENTE
A51: NO | B51: Migale | C51: Amortiguador capot | D51: 1 | E51: ebay | F51: 85 | G51: 45078 | H51: 16.99 | I51: 17.16 | J51: =I51+(I51*0.04) -> 17.8464 | K51: 5 | M51: DONE | N51: SI | P51: =F51-(J51+K51) -> 62.1536 | R51: SI | S51: UPS: 1Z256R4F0316055815 | T51: ENTREGADO A CLIENTE
A52: NO | B52: Migale | C52: plastico sapito | D52: 1 | E52: ebay | F52: 85 | G52: 45078 | H52: 40.57 | I52: 40.98 | J52: =I52+(I52*0.04) -> 42.6192 | K52: 5 | M52: DONE | N52: SI | P52: =F52-(J52+K52) -> 37.3808 | R52: SI | S52: USPS: 9405511206214676814565 | T52: ENTREGADO A CLIENTE
A53: NO | B53: Abel | C53: Front bumper convertion | D53: 1 | E53: https://ind-distribution.com/products/ind-f87-m2-competition-bumper-retrofit-kit | F53: 5230 | G53: 45078 | H53: 2730 | I53: 2741.65 | J53: =I53+(I53*0.04) -> 2851.316 | K53: 1100 | M53: DONE | N53: SI | P53: =F53-(J53+K53) -> 1278.684 | R53: SI | S53: 59576508-2 | T53: ENTREGADO A CLIENTE
A54: NO | B54: Rodri Freijedo | C54: Guardaplast honda | D54: 1 | E54: https://order.ebay.com/ord/show?/ViewPaymentStatus&purchaseOrderId=22-1012-367705#/ | F54: 160 | G54: 45079 | H54: 52.91 | I54: 53.44 | J54: =I54+(I54*0.04) -> 55.5776 | K54: 80 | M54: DONE | N54: SI | P54: =F54-(J54+K54) -> 24.4224 | R54: SI | S54: UPS: 1Z1Y11Y70320609609 | T54: ENTREGADO A CLIENTE
A55: NO | B55: Gonza Castellvi | C55: Chargepipe N55 X3 | D55: 1 | E55: vrsf | F55: 100 | G55: 45078 | H55: 0 | I55: 0 | J55: =I55+(I55*0.04) -> 0 | K55: 80 | M55: DONE | N55: SI | P55: =F55-(J55+K55) -> 20 | R55: SI | S55: Fedex: 399074428580 | T55: ENTREGADO A CLIENTE
A56: NO | B56: NERF | C56: Zapas Airmax | D56: 1 | E56: https://stockx.com/buying/14135239533479773733 | F56: 0 | H56: 160.4 | I56: 0 | J56: =I56+(I56*0.04) -> 0 | K56: 100 | M56: DONE | N56: SI | P56: =F56-(J56+K56) -> -100 | R56: SI | S56: Ups: 1Z45085V0300389210 | T56: ENTREGADO A CLIENTE
A57: NO | B57: Danno | C57: Bujes RS4 | D57: 1 | E57: kuhl rennsport | F57: 180 | H57: 0 | I57: 0 | J57: =I57+(I57*0.04) -> 0 | K57: 160 | M57: DONE | N57: SI | P57: =F57-(J57+K57) -> 20 | R57: SI | S57: USPS: 9405511206214630044137 | T57: ENTREGADO A CLIENTE
A58: NO | B58: Maximiliano | C58: Radiador bmw 135i n55 | D58: 1 | E58: https://www.ecstuning.com/b-csf-parts/radiator-bmw-x1-2-l-2015-2012bmw-135i-3-l-2012-2008bmw-335i-3-l-2012-2007bmw-335i-xdrive-3-l-2012-2009bmw-335is-3-l-2012-2011bmw-335xi-3-l-2008-2007bmw-x1-3-l-2015-2013bmw-z4-3-l-2016-2009/3717~csf/ | F58: 600 | G58: 45085 | H58: 125.21 | I58: 126.46 | J58: =I58+(I58*0.04) -> 131.5184 | K58: 180 | M58: DONE | N58: SI | P58: =F58-(J58+K58) -> 288.4816 | R58: SI | S58: fedex: 466153718915363 | T58: ENTREGADO A CLIENTE
A59: NO | B59: Migale | C59: amortiguadorcitos | D59: 2 | E59: https://www.ebay.com/itm/123556988063?epid=1630537340&hash=item1cc492049f:g:ITcAAOSw8U9cHT-y&amdata=enc%3AAQAIAAAA4Km64DIS%2F2X2Kk0xgw39bqvzBc692dtaG2YNjFhS%2BsoPHktif%2FypYjbmHuhnH9pSA7v1L6aBzHQYb3SgErSr4Ee0LBsspaDahKqnj7XGip17mXMMWuNuaCtAamJmXDwGH8lC3GlLFR5Bru14M38aBLNz9IvlDBqnKAcifP3EDn01hShyCi26oij8l0UdTBFsQVrAz0deSe8qvhtL1l%2B%2FgClfAm7XigfuaMKkDHIoX8%2FMmMyJzjfNCX%2BK4XQoYOqL4kuj%2F%2FnTeBft4Wd1IWTn9K892yIyZtIks0O5L4eMHEk%2B%7Ctkp%3ABk9SR-Su8aOXYg | F59: 250 | G59: 45091 | H59: 99 | I59: 99.99 | J59: =I59+(I59*0.04) -> 103.9896 | K59: 13 | M59: DONE | N59: SI | P59: =F59-(J59+K59) -> 133.0104 | R59: SI | S59: USPS: 9400111206215870921223 | T59: ENTREGADO A CLIENTE
A60: NO | B60: Danno | C60: Buje restante RS4 | D60: 1 | F60: 20 | G60: 45098 | H60: 0 | I60: 0 | J60: =I60+(I60*0.04) -> 0 | K60: 13 | M60: DONE | N60: SI | P60: =F60-(J60+K60) -> 7 | R60: SI | S60: USPS 9405511206215429326960 | T60: ENTREGADO A CLIENTE
A61: NO | B61: Raz | C61: Reflector delete M2 competition | D61: 1 | E61: https://www.ebay.com/itm/155227424268?hash=item242446860c:g:gCsAAOSwZQ1fC~nf&amdata=enc%3AAQAIAAAA0NWpGp3xr%2FNGf0m65rMmKlwO71qL6meGHYe5jbKinT6PfPSCFBJXGRmR47kdPWoXPpoYxP7L%2FiznQJ94q%2BvAeZ%2BFTBhhQcwqPruRclT%2BjC5Cw19w%2FOnl6eOMlzs2stmhyt%2B3OnGfzD6g89dx69tGsLJEiOKlhreUZWPqSASU%2B0iSj%2FXEprM0LDe4o%2FvPI%2B6oJL1nG3JqcdnMeSa4JFCUxE9dwjF%2FgyMUhrJEKjAIFYTOJ%2Bi%2BAPvO25MEo8LWG3ny8Z86a5vYA%2F0f75rcrd7LSUk%3D%7Ctkp%3ABk9SR7ausfqbYg | F61: 170 | G61: 45098 | H61: 114.81 | I61: 115.96 | J61: =I61+(I61*0.04) -> 120.5984 | K61: 13 | M61: DONE | N61: SI | P61: =F61-(J61+K61) -> 36.4016 | R61: SI | S61: USPS: 9405509205568732088727 | T61: ENTREGADO A CLIENTE
A62: NO | B62: NERF | C62: INTAKE | D62: 1 | E62: https://www.ebay.com/itm/403642568555 | F62: 0 | G62: 45091 | J62: =I62+(I62*0.04) -> 0 | K62: 160 | M62: DONE | N62: SI | P62: =F62-(J62+K62) -> -160 | R62: SI | S62: UPS: 1Z4X554V0311327268 | T62: ENTREGADO A CLIENTE
A63: NO | B63: Alan Olmedo | C63: Junta Cometic | D63: 1 | E63: - | F63: 440 | I63: 252.48 | J63: =I63+(I63*0.04) -> 262.5792 | K63: 80 | M63: DONE | N63: SI | P63: =F63-(J63+K63) -> 97.4208 | R63: SI | S63: DONE | T63: ENTREGADO A CLIENTE
A64: NO | B64: Alan Olmedo | C64: Getbmw | D64: 1 | E64: - | F64: 2588 | I64: 1645.61 | J64: =I64+(I64*0.04) -> 1711.4344 | K64: 280 | M64: DONE | N64: SI | P64: =F64-(J64+K64) -> 596.5656 | R64: SI | S64: DONE | T64: ENTREGADO A CLIENTE
A65: NO | B65: Alan Olmedo | C65: ECS Barra | D65: 1 | E65: - | F65: 724 | I65: 407.37 | J65: =I65+(I65*0.04) -> 423.6648 | K65: 180 | M65: DONE | N65: SI | P65: =F65-(J65+K65) -> 120.3352 | R65: SI | S65: DONE | T65: ENTREGADO A CLIENTE
A66: NO | B66: Emiliano Righetti | C66: Manguera Bmw | D66: 1 | E66: Genuine BMW - 17117541143 - Coolant Hose - Radiator to Oil Cooler (17-11-7-541-143) (ecstuning.com) | F66: 100 | G66: 45103 | H66: 53.95 | I66: 54.94 | J66: =I66+(I66*0.04) -> 57.1376 | K66: 0 | M66: DONE | N66: SI | P66: =F66-(J66+K66) -> 42.8624 | R66: SI | S66: Fedex: 74899989289339220974 | T66: ENTREGADO A CLIENTE
A67: NO | B67: Nacho Itu | C67: Opticas LED 335 | D67: 1 | E67: https://order.ebay.com/ord/show?orderId=13-10225-01490#/ | F67: 760 | G67: 45105 | H67: 394.83 | I67: 398.78 | J67: =I67+(I67*0.04) -> 414.7312 | K67: 225 | M67: DONE | N67: SI | P67: =F67-(J67+K67) -> 120.2688 | R67: SI | S67: Usps: 9361289677021605372732 | T67: ENTREGADO A CLIENTE
A68: NO | B68: Facu Godoy | C68: Rotulas Jeep Wrangler | D68: 1 | E68: https://status.roughcountry.com/#/order/0/7851886 | F68: 318 | G68: 45105 | H68: 139.05 | I68: 140.44 | J68: =I68+(I68*0.04) -> 146.0576 | K68: 135 | M68: DONE | N68: SI | P68: =F68-(J68+K68) -> 36.9424 | R68: SI | S68: Fedex: 657933100060 | T68: ENTREGADO A CLIENTE
A69: NO | B69: Alan Olmedo | C69: Bomba nafta m3 | D69: 1 | E69: https://www.ecstuning.com/Cart/Receipt-212205159/?customerID=2679329 | F69: 550 | G69: 45141 | H69: 359.41 | I69: 363 | J69: =I69+(I69*0.04) -> 377.52 | K69: 80 | M69: DONE | N69: SI | P69: =F69-(J69+K69) -> 92.48 | R69: SI | S69: Fedex: 783459607617 | T69: ENTREGADO A CLIENTE
A70: NO | B70: Javi Danno | C70: Opticas | D70: 1 | F70: 420 | G70: 45141 | H70: 0 | I70: 0 | J70: =I70+(I70*0.04) -> 0 | K70: 270 | M70: DONE | N70: SI | P70: =F70-(J70+K70) -> 150 | R70: SI | S70: UPS: 1Z9FY4100328517764 | T70: ENTREGADO A CLIENTE
A71: NO | B71: Brian Olmedo | C71: Herramienta sacabollo | D71: 1 | E71: https://app.ecwid.com/print_invoice?ownerid=266218 | F71: 143.36 | G71: 45141 | I71: 98.36 | J71: 0 | K71: 45 | M71: DONE | N71: SI | P71: 0 | R71: SI | S71: DONE | T71: ENTREGADO A CLIENTE
A72: NO | B72: NERF | C72: Boton auxiliar | D72: 1 | E72: https://order.ebay.com/ord/show?orderId=23-10234-09916#/ | F72: 0 | I72: 0 | J72: =I72+(I72*0.04) -> 0 | K72: 10 | M72: DONE | N72: SI | P72: =F72-(J72+K72) -> -10 | R72: SI | S72: USPS: 9400108205499073046469 | T72: ENTREGADO A CLIENTE
A73: NO | B73: NERF | C73: Mud guard flaps | D73: 1 | E73: https://order.ebay.com/ord/show?orderId=24-10248-11577#/ | F73: 0 | I73: 0 | J73: =I73+(I73*0.04) -> 0 | K73: 80 | M73: DONE | N73: SI | P73: =F73-(J73+K73) -> -80 | R73: SI | S73: UPS: 1Z0AX5770314211000 | T73: ENTREGADO A CLIENTE
A74: NO | B74: NERF | C74: Repuestos Honda | D74: 1 | E74: https://www.hondapartsnow.com/online/order/summary?orderId=1006551&orderGuid=9a3eab8c-1036-419d-8daa-c0d0514cde85 | F74: 0 | I74: 0 | J74: =I74+(I74*0.04) -> 0 | K74: 80 | M74: DONE | N74: SI | P74: =F74-(J74+K74) -> -80 | R74: SI | S74: fedex: 781229232866 | T74: ENTREGADO A CLIENTE
A75: NO | B75: NERF | C75: Burletes Honda | D75: 1 | E75: https://order.ebay.com/ord/show?orderId=08-10268-23565#/ | F75: 0 | I75: 0 | J75: =I75+(I75*0.04) -> 0 | K75: 10 | M75: DONE | N75: SI | P75: =F75-(J75+K75) -> -10 | R75: SI | S75: FedEx: 772680647761 | T75: ENTREGADO A CLIENTE
A76: NO | B76: NERF | C76: Consola Central | D76: 1 | E76: https://order.ebay.com/ord/show?orderId=11-10266-67398#/ | F76: 0 | I76: 0 | J76: =I76+(I76*0.04) -> 0 | M76: DONE | N76: SI | P76: =F76-(J76+K76) -> 0 | R76: SI | S76: FedEx: 780918964796 | T76: ENTREGADO A CLIENTE
A77: NO | B77: Rodrigo | C77: Selenoide Hyundai | D77: 1 | E77: https://order.ebay.com/ord/show?orderId=02-10295-29228#/ | F77: 50 | I77: 31.34 | J77: =I77+(I77*0.04) -> 32.5936 | K77: 4 | M77: DONE | N77: SI | P77: =F77-(J77+K77) -> 13.4064 | R77: SI | S77: USPS: 9400116901337306215324 | T77: ENTREGADO A CLIENTE
A78: NO | B78: NERF | C78: Volante | D78: 1 | E78: https://order.ebay.com/ord/show?orderId=03-10281-63770#/ | F78: 0 | I78: 0 | J78: =I78+(I78*0.04) -> 0 | M78: DONE | N78: SI | P78: =F78-(J78+K78) -> 0 | R78: SI | S78: FedEx: 781249482099 | T78: ENTREGADO A CLIENTE
A79: NO | B79: Rey | C79: Buje Powerflex | D79: 1 | E79: https://www.powerflexusa.com/my/invoices/250146?model=account.move&res_id=250146&access_token=e8c8184a-f9fe-468d-a475-97725270cced | F79: 140 | H79: 78.98 | I79: 79.77 | J79: =I79+(I79*0.04) -> 82.9608 | K79: 24 | M79: DONE | N79: SI | P79: =F79-(J79+K79) -> 33.0392 | R79: SI | S79: Ups: 1ZE401340396020977 | T79: ENTREGADO A CLIENTE
A80: NO | B80: NERF | C80: Faros traseros honda | D80: 1 | E80: https://order.ebay.com/ord/show?orderId=22-10327-87782#/ | F80: 0 | H80: 0 | I80: 0 | J80: =I80+(I80*0.04) -> 0 | K80: 90 | M80: DONE | N80: SI | P80: =F80-(J80+K80) -> -90 | R80: SI | S80: UPS: 1Z14V5340322237733 | T80: ENTREGADO A CLIENTE
A81: NO | B81: NERF | C81: Giros Honda | D81: 1 | E81: https://order.ebay.com/ord/show?orderId=07-10350-74068#/ | F81: 0 | H81: 0 | I81: 0 | J81: =I81+(I81*0.04) -> 0 | K81: 20 | M81: DONE | N81: SI | P81: =F81-(J81+K81) -> -20 | R81: SI | S81: USPS: RS900165582LV | T81: ENTREGADO A CLIENTE
A82: NO | B82: Juan M BMW | C82: Sensor oxigeno | D82: 1 | E82: https://www.ecstuning.com/Cart/Receipt-744703530/?customerID=2679329 | F82: 530 | G82: 45171 | H82: 367.19 | I82: 370.86 | J82: =I82+(I82*0.04) -> 385.6944 | K82: 0 | M82: DONE | N82: SI | P82: =F82-(J82+K82) -> 144.3056 | R82: SI | S82: USPS: 9400111898518425880996 | T82: ENTREGADO A CLIENTE
A83: NO | B83: Rey | C83: Stereo Audi | D83: 1 | E83: https://order.ebay.com/ord/show?orderId=25-10375-79531#/ | F83: 1050 | H83: 619.52 | I83: 625.72 | J83: =I83+(I83*0.04) -> 650.7488 | K83: 160 | M83: DONE | N83: SI | P83: =F83-(J83+K83) -> 239.2512 | R83: SI | S83: Fedex -DONE | T83: ENTREGADO A CLIENTE
A84: NO | B84: Rey | C84: manija moto | D84: 1 | E84: https://order.ebay.com/ord/show?orderId=25-10375-80045#/ | F84: 60 | I84: 40.05 | J84: =I84+(I84*0.04) -> 41.652 | K84: 0 | M84: DONE | N84: SI | P84: =F84-(J84+K84) -> 18.348 | R84: SI | S84: Global UPAAG000000053105047 | T84: ENTREGADO A CLIENTE
A85: NO | B85: Rey | C85: puños moto | D85: 1 | E85: https://order.ebay.com/ord/show?orderId=24-10390-91466#/ | F85: 50 | H85: 16.83 | I85: 17 | J85: =I85+(I85*0.04) -> 17.68 | K85: 20 | M85: DONE | N85: SI | P85: =F85-(J85+K85) -> 12.32 | R85: SI | S85: Usps 9400111206218591699754 | T85: ENTREGADO A CLIENTE
A86: NO | B86: Abel | C86: Guardabarros 335i e92 | D86: 1 | E86: https://www.amazon.com/gp/product/B07K2L6NQC/ref=ppx_yo_dt_b_asin_title_o00_s00?ie=UTF8&psc=1 | F86: 680 | H86: 182.23 | I86: 184.05 | J86: =I86+(I86*0.04) -> 191.412 | K86: 180 | M86: DONE | N86: SI | P86: =F86-(J86+K86) -> 308.588 | R86: SI | S86: Fedex -DONE | T86: ENTREGADO A CLIENTE
A87: NO | B87: Nico m3 | C87: Kit metales y bulones + Junta Carter + Alcanza cinturon | D87: 1 | E87: https://www.ecstuning.com/MyAccount/Orders/Order-757570075/ | F87: =1250+200+180 -> 1630 | H87: 1040.5 | I87: 1050.91 | J87: =I87+(I87*0.04) -> 1092.9464 | K87: 160 | M87: DONE | N87: SI | P87: =F87-(J87+K87) -> 377.0536 | R87: SI | S87: 1Z4045240390396368 | T87: ENTREGADO A CLIENTE
A88: NO | B88: Nico m3 | C88: Riñones Black Chrome | D88: 1 | E88: https://www.getbmwparts.com/account/order?token=eyJ0eXAiOiJKV1QiLCJhbGciOiJIUzUxMiJ9.eyJvcmRlcl9udW1iZXIiOiI0NDEyODI4NyIsInVzZXJfZW1haWwiOiJlbWlsaWFub0B0cmliZXNoaXBwaW5nLmNvbSJ9.VNHl9Jq-D5e7FwR7OoUbq-jLjvE0W6PFXZjkojdbNgPNKeDn_SpJMIbN-OuQOYjyk-g02Pa2kPud_KzCLzLzyw | F88: 790 | H88: 558.54 | I88: 564.13 | J88: =I88+(I88*0.04) -> 586.6952 | K88: 0 | M88: DONE | N88: SI | P88: =F88-(J88+K88) -> 203.3048 | R88: SI | S88: Fedex - 782614720297 | T88: ENTREGADO A CLIENTE
A89: NO | B89: Tahio | C89: Guia paragolpe 240 y tapita | D89: 1 | E89: https://www.bmwpartsdeal.com/online/order/summary?orderId=235912&orderGuid=fe68a369-9160-49f1-b9d1-39f03ba363a9 | F89: 160 | H89: 63.87 | I89: 64.51 | J89: =I89+(I89*0.04) -> 67.0904 | K89: 0 | M89: DONE | N89: SI | P89: =F89-(J89+K89) -> 92.9096 | R89: SI | S89: 9405511206364495662325 | T89: ENTREGADO A CLIENTE
A90: NO | B90: Rey | C90: Repuesto gomaespuma | D90: 1 | E90: https://order.ebay.com/ord/show?orderId=06-10461-31789#/ | F90: 55 | I90: 31.09 | J90: =I90+(I90*0.04) -> 32.3336 | K90: 10 | M90: DONE | N90: SI | P90: =F90-(J90+K90) -> 12.6664 | R90: SI | S90: Global: UPAAH000000053051095 | T90: ENTREGADO A CLIENTE
A91: NO | B91: Rey | C91: flotante | D91: 1 | E91: https://order.ebay.com/ord/show?orderId=10-10458-91843#/ | F91: 55 | I91: 30.66 | J91: =I91+(I91*0.04) -> 31.8864 | K91: 10 | M91: DONE | N91: SI | P91: =F91-(J91+K91) -> 13.1136 | R91: SI | S91: USPS: LE527493705DE | T91: ENTREGADO A CLIENTE
A92: NO | B92: Juanma | C92: Insignia 240 | D92: 1 | E92: https://autotecknic.com/checkouts/co/c39c3224adbba307358b788e89f02417/thank_you | F92: 140 | G92: 45167 | H92: 104.35 | I92: 105.39 | J92: =I92+(I92*0.04) -> 109.6056 | K92: 0 | M92: DONE | N92: SI | P92: =F92-(J92+K92) -> 30.3944 | R92: SI | S92: USPS: 9405511206203054752636 | T92: ENTREGADO A CLIENTE
A93: NO | B93: Emiliano Righetti | C93: Bobinas M3 x8 | D93: 8 | E93: https://www.ecstuning.com/Cart/Receipt-769305190/?customerID=2679329 | F93: 3300 | G93: 45168 | H93: 2121.08 | I93: 2142.29 | J93: =I93+(I93*0.04) -> 2227.9816 | K93: 120 | M93: DONE | N93: SI | P93: =F93-(J93+K93) -> 952.0184 | R93: SI | S93: UPS: 1Z4045240396106491 | T93: ENTREGADO A CLIENTE
A94: NO | B94: Flavio Vega | C94: Cojinetes K series | D94: 1 | E94: https://order.ebay.com/ord/show?orderId=20-10485-26250#/ | F94: 200 | G94: 45171 | H94: 117.65 | I94: 118.83 | J94: =I94+(I94*0.04) -> 123.5832 | K94: 10 | M94: DONE | N94: SI | P94: =F94-(J94+K94) -> 66.4168 | R94: SI | S94: USPS: 9400108205498118015873 | T94: ENTREGADO A CLIENTE
A95: NO | B95: Aixa | C95: Corta corrientes | D95: 1 | E95: https://order.ebay.com/ord/show?itemId=402295987768&transactionId=1178326743027&mkevt=1&mkpid=0&emsid=e11400.m144670.l152615&mkcid=7&ch=osgood&euid=a6aa402a5d9c40709e21de158bbd21cf&bu=43795160990&exe=0&ext=0&osub=-1%7E1&crd=20230906105813&segname=11400#/ | F95: 95 | G95: 45175 | H95: 38.13 | I95: 38.51 | J95: =I95+(I95*0.04) -> 40.0504 | K95: 40 | M95: DONE | N95: SI | P95: =F95-(J95+K95) -> 14.9496 | R95: SI | S95: USPS: 9235990328168001642422 | T95: ENTREGADO A CLIENTE
A96: NO | B96: Nacho Depa | C96: Valvula X6 | D96: 1 | E96: https://order.ebay.com/ord/show?/ViewPaymentStatus&purchaseOrderId=24-1051-737983#/ | F96: 90 | G96: 45176 | H96: 28.76 | I96: 29.05 | J96: =I96+(I96*0.04) -> 30.212 | K96: 10 | M96: DONE | N96: SI | P96: =F96-(J96+K96) -> 49.788 | R96: SI | S96: FedEx: 61290988122825198857 | T96: ENTREGADO A CLIENTE
A97: NO | B97: Luciano Civic SI | C97: Sexta Corta | D97: 1 | E97: https://www.megazip.net/order/642336-1 | F97: 350 | G97: 45177 | H97: 192.66 | I97: 196.13 | J97: =I97+(I97*0.04) -> 203.9752 | K97: 80 | M97: DONE | N97: SI | P97: =F97-(J97+K97) -> 66.0248 | R97: SI | S97: FedEx: 773407113963 | T97: ENTREGADO A CLIENTE
A98: NO | B98: Emiliano Rial | C98: Engine valve cover with gasket | D98: 1 | E98: Factura descargada | F98: 165 | G98: 45181 | H98: 0 | I98: 0 | J98: =I98+(I98*0.04) -> 0 | K98: 120 | M98: DONE | N98: SI | P98: =F98-(J98+K98) -> 45 | R98: SI | S98: UPS: 1Z3Y18820332415575 | T98: ENTREGADO A CLIENTE
A99: NO | B99: Ramiro Cordoba | C99: Carburador | D99: 1 | F99: 180 | I99: 0 | J99: =I99+(I99*0.04) -> 0 | K99: 135 | M99: DONE | N99: SI | P99: =F99-(J99+K99) -> 45 | R99: SI | S99: FedEx: 61299998825445922450 | T99: ENTREGADO A CLIENTE
A100: NO | B100: Abel | C100: Map n20 | D100: 1 | E100: https://www.ecstuning.com/b-continental-parts/map-sensor/13627843531~vdo/ | F100: 125 | H100: 72.75 | I100: 73.48 | J100: =I100+(I100*0.04) -> 76.4192 | K100: 14 | M100: DONE | N100: SI | P100: =F100-(J100+K100) -> 34.5808 | R100: SI | S100: USPS: 9400111898518425253332 | T100: ENTREGADO A CLIENTE
...

Sheet STOCK
I1: SUGERIDOS
A2: ID | B2: FECHA | C2: MARCA | D2: ITEM | E2: VARIANTE | F2: CANTIDAD | G2: DISPONIBLES | H2: COSTO TOTAL POR UNIDAD | I2: GANANCIA | J2: PRECIO LISTA | K2: GANANCIA EMI | L2: PRECIO EMI | M2: GANANCIA TALLER | N2: PRECIO TALLER | O2: VENTAS (ID) | P2: CONCAT
A3: 625 | B3: 45949 | C3: CTS | D3: DOWNPIPE | E3: B58 | F3: 4 | G3: 0 | H3: =176.1448+(4.5*50) -> 401.1448 | I3: 0.69515 | J3: =H3+(H3*I3) -> 680.00061 | K3: 0.5 | L3: =H3+(H3*K3) -> 601.7172 | M3: 0.55 | N3: =H3+(H3*M3) -> 621.77444 | O3: =CONCATENATE('SEGUIMIENTO COMPRAS TRIBE'!B665, ", ",'SEGUIMIENTO COMPRAS TRIBE'!B695,", ",'SEGUIMIENTO COMPRAS TRIBE'!B701,", ",'SEGUIMIENTO COMPRAS TRIBE'!B707) -> Emiliano Righetti, Emiliano Righetti, Emiliano Righetti, Emiliano Righetti | P3: =CONCATENATE(C3," ",D3," ",E3) -> CTS DOWNPIPE B58
A4: 625, 649 | B4: 45949 | C4: CTS | D4: DOWNPIPE | E4: S58 | F4: 4 | G4: 1 | H4: =518.96+(5.25*50) -> 781.46 | I4: 0.69515 | J4: =H4+(H4*I4) -> 1324.6919 | K4: 0.35 | L4: =H4+(H4*K4) -> 1054.971 | M4: 0.55 | N4: =H4+(H4*M4) -> 1211.263 | O4: =CONCATENATE('SEGUIMIENTO COMPRAS TRIBE'!B662, ", ", 'SEGUIMIENTO COMPRAS TRIBE'!B663) -> Santiago Ventana, Emiliano Alcaide | P4: =CONCATENATE(C4," ",D4," ",E4) -> CTS DOWNPIPE S58
A5: 624 | B5: 45949 | C5: Infinity Design | D5: INTAKE | E5: B58 G42 | F5: 1 | G5: 0 | H5: 1223.07 | I5: 0.4 | J5: =H5+(H5*I5) -> 1712.298 | K5: 0.2 | L5: =H5+(H5*K5) -> 1467.684 | M5: 0.25 | N5: =H5+(H5*M5) -> 1528.8375 | O5: =CONCATENATE('SEGUIMIENTO COMPRAS TRIBE'!B708, ", ") -> Emiliano Righetti, | P5: =CONCATENATE(C5," ",D5," ",E5) -> Infinity Design INTAKE B58 G42
A6: 623 | B6: 45950 | C6: NGK | D6: Bujias | E6: B58/S58 | F6: 10 | G6: 6 | H6: 98.2 | I6: 0.525 | J6: =H6+(H6*I6) -> 149.755 | K6: 0.325 | L6: =H6+(H6*K6) -> 130.115 | M6: 0.425 | N6: =H6+(H6*M6) -> 139.935 | O6: =CONCATENATE('SEGUIMIENTO COMPRAS TRIBE'!B661, ", ",'SEGUIMIENTO COMPRAS TRIBE'!B664 , ", ", 'SEGUIMIENTO COMPRAS TRIBE'!B679,", ",'SEGUIMIENTO COMPRAS TRIBE'!B682) -> Mauro Lerda, Santiago Ventana, Emiliano Righetti, Javier Pergamino | P6: =CONCATENATE(C6," ",D6," ",E6) -> NGK Bujias B58/S58
A7: 676 | B7: 45973 | C7: Infinity Design | D7: INTAKE | E7: S58 | F7: 2 | G7: 1 | H7: 2225 | I7: 0.4 | J7: =H7+(H7*I7) -> 3115 | K7: 0.2 | L7: =H7+(H7*K7) -> 2670 | M7: 0.25 | N7: =H7+(H7*M7) -> 2781.25 | O7: =CONCATENATE('SEGUIMIENTO COMPRAS TRIBE'!B687, ", ") -> Santiago Ventana, | P7: =CONCATENATE(C7," ",D7," ",E7) -> Infinity Design INTAKE S58
A8: 696 | B8: 46001 | C8: Generica | D8: Rejillas | E8: M2 G87 | F8: 5 | G8: 4 | H8: 80.4 | I8: 0.5 | J8: =H8+(H8*I8) -> 120.6 | K8: 0.25 | L8: =H8+(H8*K8) -> 100.5 | M8: 0.37 | N8: =H8+(H8*M8) -> 110.148 | O8: =CONCATENATE('SEGUIMIENTO COMPRAS TRIBE'!B765, ", ") -> Emiliano Alcaide, | P8: =CONCATENATE(C8," ",D8," ",E8) -> Generica Rejillas M2 G87
A9: 713 | B9: 46001 | C9: Infinity Design | D9: INTAKE | E9: B58 G42 | F9: 3 | G9: 3 | H9: 1158 | I9: 0.479 | J9: =H9+(H9*I9) -> 1712.682 | K9: 0.265 | L9: =H9+(H9*K9) -> 1464.87 | M9: 0.32 | N9: =H9+(H9*M9) -> 1528.56
A10: 719 | B10: 46001 | C10: CTS | D10: DOWNPIPE | E10: B58 | F10: 9 | G10: 8 | H10: 398 | I10: 0.6952 | J10: =H10+(H10*I10) -> 674.6896 | K10: 0.5 | L10: =H10+(H10*K10) -> 597 | M10: 0.55 | N10: =H10+(H10*M10) -> 616.9 | O10: =CONCATENATE('SEGUIMIENTO COMPRAS TRIBE'!B767, ", ") -> Emiliano Righetti, | P10: =CONCATENATE(C10," ",D10," ",E10) -> CTS DOWNPIPE B58
I11: 0 | J11: =H11+(H11*I11) -> 0 | K11: 0 | L11: =H11+(H11*K11) -> 0 | M11: 0 | N11: =H11+(H11*M11) -> 0
I12: 0 | J12: =H12+(H12*I12) -> 0 | K12: 0 | L12: =H12+(H12*K12) -> 0 | M12: 0 | N12: =H12+(H12*M12) -> 0
I13: 0 | J13: =H13+(H13*I13) -> 0 | K13: 0 | L13: =H13+(H13*K13) -> 0 | M13: 0 | N13: =H13+(H13*M13) -> 0
I14: 0 | J14: =H14+(H14*I14) -> 0 | K14: 0 | L14: =H14+(H14*K14) -> 0 | M14: 0 | N14: =H14+(H14*M14) -> 0
C15: Caja al 26/02/2026 (dinero disponible) | D15: =5217.98-3150 -> 2067.98 | I15: 0 | J15: =H15+(H15*I15) -> 0 | K15: 0 | L15: =H15+(H15*K15) -> 0 | M15: 0 | N15: =H15+(H15*M15) -> 0
I16: 0 | J16: =H16+(H16*I16) -> 0 | K16: 0 | L16: =H16+(H16*K16) -> 0 | M16: 0 | N16: =H16+(H16*M16) -> 0
I17: 0 | J17: =H17+(H17*I17) -> 0 | K17: 0 | L17: =H17+(H17*K17) -> 0 | M17: 0 | N17: =H17+(H17*M17) -> 0
I18: 0 | J18: =H18+(H18*I18) -> 0 | K18: 0 | L18: =H18+(H18*K18) -> 0 | M18: 0 | N18: =H18+(H18*M18) -> 0
I19: 0 | J19: =H19+(H19*I19) -> 0 | K19: 0 | L19: =H19+(H19*K19) -> 0 | M19: 0 | N19: =H19+(H19*M19) -> 0
I20: 0 | J20: =H20+(H20*I20) -> 0 | K20: 0 | L20: =H20+(H20*K20) -> 0 | M20: 0 | N20: =H20+(H20*M20) -> 0
I21: 0 | J21: =H21+(H21*I21) -> 0 | K21: 0 | L21: =H21+(H21*K21) -> 0 | M21: 0 | N21: =H21+(H21*M21) -> 0
I22: 0 | J22: =H22+(H22*I22) -> 0 | K22: 0 | L22: =H22+(H22*K22) -> 0 | M22: 0 | N22: =H22+(H22*M22) -> 0
I23: 0 | J23: =H23+(H23*I23) -> 0 | K23: 0 | L23: =H23+(H23*K23) -> 0 | M23: 0 | N23: =H23+(H23*M23) -> 0
I24: 0 | J24: =H24+(H24*I24) -> 0 | K24: 0 | L24: =H24+(H24*K24) -> 0 | M24: 0 | N24: =H24+(H24*M24) -> 0
I25: 0 | J25: =H25+(H25*I25) -> 0 | K25: 0 | L25: =H25+(H25*K25) -> 0 | M25: 0 | N25: =H25+(H25*M25) -> 0
I26: 0 | J26: =H26+(H26*I26) -> 0 | K26: 0 | L26: =H26+(H26*K26) -> 0 | M26: 0 | N26: =H26+(H26*M26) -> 0
I27: 0 | J27: =H27+(H27*I27) -> 0 | K27: 0 | L27: =H27+(H27*K27) -> 0 | M27: 0 | N27: =H27+(H27*M27) -> 0
... I33: 0 | J33: =H33+(H33*I33) -> 0 | K33: 0 | L33: =H33+(H33*K33) -> 0 | M33: 0 | N33: =H33+(H33*M33) -> 0

Sheet REPRO
A1: FECHA | B1: CODIGO | C1: COSTO | D1: PRECIO | E1: USADA | F1: CLIENTE | G1: Ganancia | H1: SALDADO COSTO DE LICENCIA | I1: SALDADAS US | J1: ABONADA A | K1: ABONADA POR CLIENTE/EMI
A2: 45236 | B2: 984D005F-4B74-4F97-857D-D74086F4AC5D | C2: 424 | D2: N/A | E2: TRUE | F2: LUIS BIG TURBO | G2: n/a | H2: SI | I2: SI | J2: FEDE | K2: SI | L2: Your permanent license discount code is:
A3: 45237 | B3: 99BEF756-B80B-4725-8146-79C956DF9DEB | C3: 424 | D3: 600 | E3: TRUE | F3: EMILIANO RIGHETTI | G3: =D3-C3 -> 176 | H3: SI | I3: SI | J3: FEDE | K3: SI | M3: BMA30WSD
A4: 45238 | B4: E631335F-0B21-4A8E-A47C-E811AAB4A46F | C4: 424 | D4: 600 | E4: TRUE | F4: EMILIANO RIGHETTI | G4: =D4-C4 -> 176 | H4: SI | I4: SI | J4: FEDE | K4: SI | L4: Your permanent hardware discount code is:
A5: 45239 | B5: 036C7E28-606A-4003-A006-BEB9808765F2 | C5: 424 | D5: 750 | E5: TRUE | F5: 140i AZUL RICKY | G5: =D5-C5 -> 326 | H5: SI | I5: SI | J5: FEDE | K5: SI | M5: BMA15HDW
A6: 45240 | B6: B16454C8-EBDC-4736-B6FF-0451A2A46838 | C6: 424 | D6: 750 | E6: TRUE | F6: 328I N20 RICKY | G6: =D6-C6 -> 326 | H6: SI | I6: SI | J6: FEDE | K6: SI
A7: 45433 | B7: MHD | C7: 187 | D7: 400 | E7: TRUE | F7: 13I N54 RICKY | G7: =D7-C7 -> 213 | H7: SI | I7: SI | J7: FEDE | K7: SI
A8: 45436 | B8: B20BBDF1-4AD1-4EA6-8AC0-813F35535038 | C8: 416.5 | D8: 700 | E8: TRUE | F8: X4 RICKY | G8: =D8-C8 -> 283.5 | H8: SI | I8: SI | J8: FEDE | K8: SI
A9: 45513 | B9: 6A88B923-7F95-4CAF-8BE0-100B16DB32AD | C9: =416.5+(416.5*0.04) -> 433.16 | D9: N/A | E9: TRUE | F9: Hernan Franchina 240 G42 | G9: n/a | H9: SI | I9: SI | J9: FEDE | K9: SI | M9: COSTO UNLOCK+LICENCIA | N9: =700+375 -> 1075
A10: 45525 | B10: 43584210-8F92-4028-A936-9F9E711866A4 | C10: =416.5+(416.5*0.04) -> 433.16 | D10: N/A | E10: TRUE | F10: Ferzilla | G10: n/a | H10: SI | I10: SI | J10: FEDE | K10: SI
A11: 45525 | B11: F3ECAD8D-0144-46B2-B19A-C0D3C4B6C872 | C11: =50+(50*0.04) -> 52 | D11: 52 | E11: TRUE | F11: EMILIANO RIGHETTI | G11: =D11-C11 -> 0 | H11: SI | I11: SI | J11: FEDE | K11: SI | M11: PRECIOS de referencia
A12: 45530 | B12: ABA1D9AD-C427-4EA7-8D40-72FA121BFDA7 | C12: =416.5+(416.5*0.04) -> 433.16 | D12: 567 | E12: TRUE | F12: EMILIANO RIGHETTI | G12: =D12-C12 -> 133.84 | H12: SI | I12: SI | J12: FEDE | K12: SI | M12: ITEM | N12: PRECIO LISTA | O12: DESC EMI | P12: PRECIO EMI | Q12: DESC TALLER | R12: PRECIO TALLER
A13: 45624 | B13: 5489F26F-C8DE-4917-B1A9-565AADF515A4 | C13: =416.5+(416.5*0.04) -> 433.16 | D13: 567 | E13: TRUE | F13: EMILIANO RIGHETTI | G13: =D13-C13 -> 133.84 | H13: SI | I13: SI | J13: FEDE | K13: SI | M13: REPRO FEMTO NON-M | N13: 2500 | O13: 0.06 | P13: =N13-(N13*O13) -> 2350 | Q13: 0.04 | R13: =N13-(N13*Q13) -> 2400
A14: 45301 | B14: 6508DE4-E37F-4025-835E-1457B06ABE32 | C14: 416.5 | D14: 700 | E14: TRUE | F14: 120I B48 RICKY | G14: =D14-C14 -> 283.5 | H14: SI | I14: SI | J14: FEDE | K14: SI | M14: REPRO FEMTO M | N14: 2700 | O14: 0.06 | P14: =N14-(N14*O14) -> 2538 | Q14: 0.04 | R14: =N14-(N14*Q14) -> 2592
A15: 45301 | B15: F2213172-CB14-4CF1-9100-448E2B3BA568 | C15: 416.5 | D15: 0 | E15: TRUE | F15: GEROCHIVO CLAVADO | G15: =D15-C15 -> -416.5 | H15: SI | I15: SI | J15: FEDE | K15: SI | M15: REPRO BM3 NON-M | N15: 700 | O15: 0.19 | P15: =N15-(N15*O15) -> 567 | Q15: 0.1 | R15: =N15-(N15*Q15) -> 630
A16: 45700 | B16: 32253872-D3EE-4035-9C1E-C9BEE46046FE | C16: =416.5+(416.5*0.04) -> 433.16 | D16: 567 | E16: TRUE | F16: NICO MAGGI | G16: =D16-C16 -> 133.84 | H16: SI | I16: SI | J16: FEDE | K16: SI | M16: REPRO BM3 M | N16: 700 | O16: 0.19 | P16: =N16-(N16*O16) -> 567 | Q16: 0.1 | R16: =N16-(N16*Q16) -> 630
A17: 45737 | B17: E8B88CD9-6A01-4166-9848-D0F3551AAC2D | C17: 0 | D17: 0 | E17: TRUE | F17: EMILIANO RIGHETTI - UNLOCK G42 - MANUEL VAZQUEZ | G17: 0 | H17: SI | I17: SI | J17: FEDE | K17: SI
A18: 45741 | B18: E871F0DC-A1C7-47B7-84D4-3C0F0E121C9C | C18: =433.16 -> 433.16 | D18: 567 | E18: TRUE | F18: EMILIANO RIGHETTI - JONY LALLITA | G18: =D18-C18 -> 133.84 | H18: SI | I18: SI | J18: FEDE | K18: SI | M18: PROPUESTA
A19: 45785 | B19: 4BBB1328-5F13-4C14-A1E5-9B827A146BF4 | C19: =433.16 -> 433.16 | D19: 567 | E19: TRUE | F19: EMILIANO RIGHETTI - robertonicolaspierce@gmail.com - AD616TJ | G19: =D19-C19 -> 133.84 | H19: SI | I19: SI | J19: FEDE | K19: SI | M19: REPRO FEMTO AMBAS | N19: 2200 | O19: 0.06 | P19: =N19-(N19*O19) -> 2068 | Q19: 0.04 | R19: =N19-(N19*Q19) -> 2112
A20: 45791 | B20: 45AAD44D-33A3-4D4A-8C2D-1414980D2641 | C20: =433.16 -> 433.16 | D20: 567 | E20: TRUE | F20: EMILIANO RIGHETTI - thiagomoro09@gmail.com - AD842VD | G20: =D20-C20 -> 133.84 | H20: SI | I20: SI | J20: FEDE | K20: SI | M20: REPRO FEMTO COMBO | N20: 1500 | O20: 0.06 | P20: =N20-(N20*O20) -> 1410 | Q20: 0.04 | R20: =N20-(N20*Q20) -> 1440
A21: 45793 | B21: 8C79CD09-9235-4B09-A46C-597B2BE0380F | C21: =433.16 -> 433.16 | D21: 567 | E21: TRUE | F21: EMILIANO RIGHETTI - uri.galanis@gmail.com - ac674ah | G21: =D21-C21 -> 133.84 | H21: SI | I21: SI | J21: FEDE | K21: SI
A22: 45849 | B22: 09055F98-597C-4EB0-98D3-490321A0B51B | C22: =433.16 -> 433.16 | D22: 550 | E22: TRUE | F22: ALAN OLMEDO - Tito comparato - N20 | G22: =D22-C22 -> 116.84 | H22: SI | I22: SI | J22: FEDE | K22: SI
A23: 45854 | B23: A35DD6B7-8C98-4D86-A3D8-54F7ED4FB944 | C23: 433.16 | D23: 567 | E23: TRUE | F23: EMILIANO RIGHETTI - maxiplaza80@gmail.com - AB529LV | G23: =D23-C23 -> 133.84 | H23: SI | I23: SI | J23: FEDE | K23: SI
A24: 45855 | B24: ECEDD916-DF51-43DB-8B07-76BE500831C9 | C24: 0 | D24: n/a | E24: TRUE | F24: Juli Lerda - M2 - Repro G Series | G24: 0 | H24: SI | I24: SI | J24: FEDE | K24: SI
A25: 45859 | B25: 990DF998-7293-4376-A82F-D717694EBB81 | C25: 626.5 | D25: 763 | E25: TRUE | F25: EMILIANO RIGHETTI - muruzabal77@gmail.com - AD381DQ | G25: =D25-C25 -> 136.5 | H25: SI | I25: SI | J25: FEDE | K25: SI
A26: 45860 | B26: 583B2FF6-2075-412B-82A3-C867BB1ECE13 | C26: 433.16 | D26: 567 | E26: TRUE | F26: EMILIANO RIGHETTI - b48 430 | G26: =D26-C26 -> 133.84 | H26: SI | I26: SI | J26: FEDE | K26: SI
A27: 45862 | B27: 11696C04-21F2-446A-8F3E-ACF5D22857BD | C27: 0 | D27: n/a | E27: TRUE | F27: Veleta - M2 G87 - Repro G series | G27: 0 | H27: SI | I27: SI | J27: FEDE | K27: SI
A28: 45869 | B28: LICENCE | C28: 325 | D28: 325 | E28: TRUE | F28: 135i e82 | G28: =D28-C28 -> 0 | H28: SI | I28: SI | J28: FEDE | K28: SI
A29: 45882 | B29: F7B8F744-8582-4745-A6E6-EFD6DCC23873 | C29: 0 | D29: Unlock | E29: TRUE | F29: Tomas Graben - 240i G42 - Repro G Series | G29: 0 | H29: SI | I29: SI | J29: FEDE | K29: SI
A30: 45883 | B30: 43074D0A-9772-443D-BEEB-29B2AA083E6D | C30: 0 | D30: Unlock | E30: TRUE | F30: RASPAGLIESI - M2 G87 - Repro G Series | G30: 0 | H30: SI | I30: SI | J30: FEDE | K30: SI
A31: 45887 | B31: F82798C3-CE44-4098-95A1-E612D494B1FA | C31: 433.16 | D31: 567 | E31: TRUE | F31: Emiliano Righetti - 335 - | G31: =D31-C31 -> 133.84 | H31: SI | I31: SI | J31: FEDE | K31: SI
A32: 45895 | B32: C5232B9C-1AEB-41FB-BC28-F073E0B0ACF1 | C32: 433.16 | D32: 567 | E32: TRUE | F32: Emiliano Righetti - 140 - santiszmulewicz@gmail.com - AC584RQ | G32: =D32-C32 -> 133.84 | H32: SI | I32: SI | J32: FEDE | K32: SI
A33: 45898 | B33: 3001338A-74C1-41BB-A7C0-89B5129D0C97 | C33: 433.16 | D33: 567 | E33: TRUE | F33: Emiliano Righetti - Chef - | G33: =D33-C33 -> 133.84 | H33: SI | I33: SI | J33: FEDE | K33: SI
A34: 45912 | B34: 56704954-3714-4498-BE2E-E289B7267BE3 | C34: 433.16 | D34: 567 | E34: TRUE | F34: Emiliano Righetti - 140 - Losfiore@gmail.com | G34: =D34-C34 -> 133.84 | H34: SI | I34: SI | J34: FEDE | K34: SI
A35: 45923 | B35: A5DA8F44-2822-40CE-8E3C-3B6CD24F7F05 | C35: 0 | D35: Unlock | E35: TRUE | F35: Leonardo Abdine - M240i G42 - Repro G Series | G35: - | H35: SI | I35: SI | J35: FEDE | K35: SI
A36: 45923 | B36: 4FDC25B4-4824-4DEA-8463-F977D413FC13 | C36: 0 | D36: Unlock | E36: TRUE | F36: Brian Lee - M240i G42 - Repro G Series | G36: - | H36: SI | I36: SI | J36: FEDE | K36: SI
A37: 45929 | B37: 8896ACAC-8656-4D01-9398-EEC7F805C870 | C37: 433.16 | D37: 567 | E37: TRUE | F37: Emiliano Righetti - Lucasjamus@hotmail.com - AE743LU | G37: =D37-C37 -> 133.84 | H37: SI | I37: SI | J37: FEDE | K37: SI
A38: 45933 | B38: C181B552-C0EB-4727-900B-BC05F765FD74 | C38: 60 | D38: 110 | E38: TRUE | F38: Emiliano Righetti - OTS Map Bundle - frigorificonazca@yahoo.com.ar | G38: =D38-C38 -> 50 | H38: SI | I38: SI | J38: FEDE | K38: SI
A39: 45924 | B39: CS Flash | C39: 307 | D39: 497.5 | E39: TRUE | F39: M2 Nacho Caparros | G39: =D39-C39 -> 190.5 | H39: SI | I39: SI | J39: FEDE | K39: SI
A40: 45924 | B40: CS Steering & Audio profile | C40: 178 | D40: 178 | E40: TRUE | F40: M2 Emiliano Righetti | G40: =D40-C40 -> 0 | H40: SI | I40: SI | J40: FEDE | K40: SI
A41: 45924 | B41: CS Steering & chassis | C41: 190 | D41: 288 | E41: TRUE | F41: M2 Fran Raspagliesi | G41: =D41-C40 -> 110 | H41: SI | I41: SI | J41: FEDE | K41: SI
A42: 45937 | B42: 6AE44506-D90C-44A3-9C97-CF46FA6A2E56 | C42: 0 | D42: Unlock | E42: TRUE | F42: Mauro Lerda - M2 G87 - repro G series | G42: =D42-C42 -> #VALUE! | H42: SI | I42: SI | J42: NAHUE | K42: SI
A43: 45943 | B43: 01190124-A430-4A90-8D4F-E693B3B0D67A | C43: 0 | D43: Unlock | E43: TRUE | F43: Santiago Ventana - M2 G87 - Repro G series | G43: =D43-C43 -> #VALUE! | H43: SI | I43: SI | J43: NAHUE | K43: SI
A44: 45944 | B44: A8F5611C-FBD4-4BB1-BD5C-C17E8FAB748D | C44: 0 | D44: Unlock | E44: TRUE | F44: Ezequiel - M2 G87 - Repro G series | G44: =D44-C44 -> #VALUE! | H44: SI | I44: SI | J44: NAHUE | K44: SI
A45: 45944 | B45: 4E676B8F-C7DC-4062-B90C-BA37796C0E99 | C45: 433.16 | D45: 567 | E45: TRUE | F45: Emiliano Righetti - servinjuancruz24@gmail.com - ab676ok | G45: =D45-C45 -> 133.84 | H45: SI | I45: SI | J45: FEDE | K45: SI
A46: 45951 | B46: A1DABFBA-2B09-48EA-9060-908152300734 | C46: 433.16 | D46: 567 | E46: TRUE | F46: Emiliano Righetti - ezequielguarizola@hotmail.com - ae074nv | G46: =D46-C46 -> 133.84 | H46: SI | I46: SI | J46: NAHUE | K46: SI
A47: 45955 | B47: F706EBAB-1D74-4361-8667-E6E890D59A84 | C47: 0 | D47: Unlock | E47: TRUE | F47: Emiliano Alcaide - M2 G87 - Repro G series | G47: =D47-C47 -> #VALUE! | H47: SI | I47: SI | J47: NAHUE | K47: SI
A48: 45960 | B48: BA17B342-7BCB-47E1-A864-4FD0F228E8E0 | C48: 52 | D48: 110 | E48: TRUE | F48: Emiliano Righetti - OTS Map Bundle - losfiore@gmail.com | G48: =D48-C48 -> 58 | H48: SI | I48: SI | J48: NAHUE | K48: SI
A49: 45965 | B49: D5FC3C07-5117-4472-9A31-987A5834037F | C49: 0 | D49: Unlock | E49: TRUE | F49: Lucas - 240 G42 - Repro G series | G49: =D49-C49 -> #VALUE! | H49: SI | I49: SI | J49: NAHUE | K49: SI
A50: 45987 | B50: C7FB9CC8-4E65-4725-9455-3BF7CB6ECA69 | C50: 0 | D50: Unlock | E50: TRUE | F50: Andres Jacobs - 340 G20 - Repro G series | G50: =D50-C50 -> #VALUE! | H50: SI | I50: SI | J50: NAHUE | K50: SI
A51: 45989 | B51: B348BD5C-C776-487A-BF45-476CAE09CC52 | C51: 433.16 | D51: 570 | E51: TRUE | F51: Alan Olmedo - BMW 220 - felipelavandeira06@gmail.com - ad472gg | G51: =D51-C51 -> 136.84 | H51: SI | I51: SI | J51: NAHUE | K51: SI
A52: 45993 | B52: 64A4A489-A372-4E05-AAE2-6FA064F27075 | C52: 0 | D52: Unlock | E52: TRUE | F52: Maxi bonemberg 240i G42 - Repro G series | G52: =D52-C52 -> #VALUE! | H52: SI | I52: SI | J52: FEDE | K52: SI
A53: 45993 | B53: 8212E62A-7BA3-42C5-B24D-82E8B8A5B9D9 | C53: 0 | D53: Unlock | E53: TRUE | F53: Fran MDQ 240i G42 - Repro G SERIES | G53: =D53-C53 -> #VALUE! | H53: SI | I53: SI | J53: FEDE | K53: SI
A54: 45994 | B54: 60E221FB-3133-4AB4-B86C-F0A5CCDF0817 | C54: 0 | D54: Unlock | E54: TRUE | F54: Guido - M2 G87 FROZEN BLUE - Repro G SERIES | G54: =D54-C54 -> #VALUE! | H54: SI | I54: SI | J54: FEDE | K54: SI
A55: 45994 | B55: 652106DA-05DA-42C7-9EC1-C4A482175AA8 | C55: 0 | D55: Unlock | E55: TRUE | F55: Emilio Tevini - M2 G87 FROZEN GRAY - Repro G SERIES | G55: =D55-C55 -> #VALUE! | H55: SI | I55: SI | J55: FEDE | K55: SI
A56: 45994 | B56: 0426F2CA-7917-4666-AFB3-B9AEAA6E47D2 | C56: 0 | D56: Unlock | E56: TRUE | F56: Andres Monteiro - M2 G87 Celeste - Repro G SERIES | G56: =D56-C56 -> #VALUE! | H56: SI | I56: NO | J56: Sin abonar | K56: NO
A57: 45994 | B57: D3DB1E24-F262-48F2-BC7E-CC8290C810E6 | C57: 0 | D57: Unlock | E57: TRUE | F57: Agustin Cicarelli - G42 240i Negro - Repro G SERIES | G57: =D57-C57 -> #VALUE! | H57: SI | I57: NO | J57: Sin abonar | K57: NO
A58: 45994 | B58: 6DC217A2-CF82-44C2-8795-5DAC13145402 | C58: 357 | D58: 567 | E58: TRUE | F58: Emiliano Righetti - Lucero Escalante - catalinasalituri@gmail.com - af187of | G58: =D58-C58 -> 210 | H58: SI | I58: NO | J58: Sin abonar | K58: NO
A59: 45994 | B59: 22536AAF-9AA8-4EB3-B34F-6D48EB7636FF | C59: 357 | D59: 0 | E59: FALSE | G59: =C59-#REF! -> #REF! | H59: SI | I59: NO | J59: Sin abonar | K59: NO
A60: 45994 | B60: FEDAC735-E72D-4FAA-9AC8-17A766C6D021 | C60: 357 | D60: 0 | E60: FALSE | G60: =C60-#REF! -> #REF! | H60: SI | I60: NO | J60: Sin abonar | K60: NO
A61: 45994 | B61: B91274D1-80E2-48B4-8F72-7F7992C81686 | C61: 357 | D61: 0 | E61: FALSE | G61: =C61-#REF! -> #REF! | H61: SI | I61: NO | J61: Sin abonar | K61: NO
A62: 46009 | B62: CS Steering & chassis | C62: 185 | D62: 292 | E62: TRUE | F62: Emiliano Righetti - M2 Frozen blue | G62: =D62-C62 -> 107 | H62: SI | I62: SI | J62: FEDE | K62: SI
A63: 46037 | B63: MHD N55E Stage 2 | C63: 330 | D63: 440 | E63: TRUE | F63: Emiliano Righetti | G63: =D63-C63 -> 110 | H63: SI | I63: SI | J63: FEDE | K63: SI
A64: 46038 | B64: Map bundle | C64: 50 | D64: 50 | E64: TRUE | F64: Emiliano Righetti | G64: =D64-C64 -> 0 | H64: SI | I64: SI | J64: FEDE | K64: SI
A65: 46042 | B65: Map bundle | C65: 100 | D65: 125 | E65: TRUE | F65: Emiliano Righetti - compras@pgstools.com.ar | G65: =D65-C65 -> 25 | H65: SI | I65: SI | J65: FEDE | K65: SI
A66: 46049 | B66: Map bundle | C66: 150 | D66: 200 | E66: TRUE | F66: Emiliano Righetti - m5 s63 - memuruzabal@hotmail.com.ar | G66: =D66-C66 -> 50 | H66: SI | I66: SI | J66: FEDE | K66: SI
E67: FALSE | G67: =D67-C67 -> 0 | H67: NO | I67: NO | J67: Sin abonar | K67: NO
E68: FALSE | G68: =D68-C68 -> 0 | H68: NO | I68: NO | J68: Sin abonar | K68: NO
E69: FALSE | G69: =D69-C69 -> 0 | H69: NO | I69: NO | J69: Sin abonar | K69: NO
E70: FALSE | G70: =D70-C70 -> 0 | H70: NO | I70: NO | J70: Sin abonar | K70: NO
E71: FALSE | G71: =D71-C71 -> 0 | H71: NO | I71: NO | J71: Sin abonar | K71: NO
E72: FALSE | G72: =D72-C72 -> 0 | H72: NO | I72: NO | J72: Sin abonar | K72: NO
E73: FALSE | G73: =D73-C73 -> 0 | H73: NO | I73: NO | J73: Sin abonar | K73: NO
E74: FALSE | G74: =D74-C74 -> 0 | H74: NO | I74: NO | J74: Sin abonar | K74: NO
E75: FALSE | G75: =D75-C75 -> 0 | H75: NO | I75: NO | J75: Sin abonar | K75: NO
E76: FALSE | G76: =D76-C76 -> 0 | H76: NO | I76: NO | J76: Sin abonar | K76: NO
E77: FALSE | G77: =D77-C77 -> 0 | H77: NO | I77: NO | J77: Sin abonar | K77: NO
E78: FALSE | G78: =D78-C78 -> 0 | H78: NO | I78: NO | J78: Sin abonar | K78: NO
... E80: FALSE | G80: =D80-C80 -> 0 | H80: NO | I80: NO | J80: Sin abonar | K80: NO

Sheet PAQUETES
A3: COSTO APROX FEMTO UNLOCK | B3: =REPRO!N9 -> 1075 | E3: GANANCIAS
A4: COSTO BAJADA B58 | B4: =STOCK!H10 -> 398 | E4: LISTA | F4: TALLER | G4: EMI
A5: COSTO BAJADA S58 | B5: =STOCK!H4 -> 781.46 | E5: 0.4 | F5: 0.3 | G5: 0.2
A6: COSTO INFINITY B58 | B6: =STOCK!H9 -> 1158
A7: COSTO INFINITY S58 | B7: =STOCK!H7 -> 2225
A8: COSTO BUJIAS TITAN | B8: =STOCK!H6 -> 98.2
A12: COSTO | B12: PAQUETE B58 | C12: LISTA | D12: TALLER | E12: EMI | H12: PAQUETE S58
A13: BAJADA | B13: =B4 -> 398 | C13: =B13*E5 -> 159.2 | D13: =B13*F5 -> 119.4 | E13: =B13*G5 -> 79.6 | H13: =B5 -> 781.46
A14: INTAKE | B14: =B6 -> 1158 | C14: =B14*E5 -> 463.2 | D14: =B14*F5 -> 347.4 | E14: =B14*G5 -> 231.6 | H14: =B7 -> 2225
A15: BUJIAS | B15: =B8 -> 98.2 | C15: =B15*E5 -> 39.28 | D15: =B15*F5 -> 29.46 | E15: =B15*G5 -> 19.64 | H15: =B8 -> 98.2
A16: REPRO | B16: =B3 -> 1075 | C16: =B16*E5 -> 430 | D16: =B16*F5 -> 322.5 | E16: =B16*G5 -> 215 | H16: =B3 -> 1075
A17: TOTAL | B17: =SUM(B13:B16) -> 2729.2 | C17: =SUM(C13:C16) -> 1091.68 | D17: =SUM(D13:D16) -> 818.76 | E17: =SUM(E13:E16) -> 545.84 | H17: =SUM(H13:H16) -> 4179.66
A19: SIN INTAKE | B19: =SUM(B13,B15,B16) -> 1571.2 | H19: =SUM(H13,H15,H16) -> 1954.66

Sheet DETALLE DE PAGOS ENVIOS A APCAR
A1: ENVIOS Y PAGOS
A3: ITEM | B3: ENVIO ABONADO | C3: PAGADO POR | D3: SALDADO? | F3: GANANCIA SELECCIONADA
A4: PARTES GETBMW M3 E36 | B4: 280 | C4: FEDE | D4: SI | F4: GANANCIA TOTAL
A5: PARTES ECS M3 E36 | B5: 160 | C5: FEDE | D5: SI
A6: JUNTA COMETIC | B6: 80 | C6: FEDE | D6: SI | F6: OTRAS CONSIDERACIONES
A7: CHAPON WRX | B7: 160 | C7: FEDE | D7: SI | F7: ITEM | G7: VALOR | H7: OBSERVACIONES
A8: GUARDAPLAST WRX | B8: 40 | C8: FEDE Y NAHUE | D8: SI | F8: DINERO PARA SALDO COMPRAS | G8: 2000 | H8: ENTREGADO A NAHUE 16/07/2024
A9: PASARUEDAS WRX | B9: 40 | C9: NAHUE | D9: SI
A10: BOMBA WALBRO | B10: 40 | C10: FEDE | D10: SI
A11: PASTILLAS HAWK | B11: 40 | C11: FEDE | D11: SI
A12: TECLADO NAHUE | B12: N/A | C12: N/A | D12: SI
A13: ESCAPE AKRAPOVIC | B13: 120 | C13: FEDE | D13: SI
A14: PARTES VOLVO GENUINE | B14: 525 | C14: FEDE | D14: SI | F14: PAGOS CUESTIONES ADMINISTRATIVAS TRIBE SHIPPING
A15: OPTICA VOLVO DER | B15: 225 | C15: FEDE | D15: SI | F15: ITEM | G15: VALOR | H15: OBSERVACIONES
A16: OPTICA VOLVO IZQ | B16: 225 | C16: FEDE | D16: SI | F16: GASTOS PUBLICIDAD Y VARIOS SALDADOS A JUNIO-2024 | G16: OK
A17: INTERFAZ VOLVO | B17: 13 | C17: FEDE | D17: SI | F17: Renovacion de dominio | G17: 22.17 | H17: pagado por nahue 16/07/2024
A18: PLASTICO VOLVO EBAY | B18: 80 | C18: FEDE | D18: SI | F18: BimmerFest | G18: 67 | H18: 17/10/2025 transfe Fede
A19: PARTES MARGOSIAN 1ER PARTE | B19: 180 | C19: FEDE | D19: SI | F19: BimmerFest | G19: 138 | H19: 03/12/2025 transfe Fede
A20: PARAGOLPE M3 E36 | B20: 480 | C20: FEDE | D20: SI | F20: Pago cartel TribeShipping para bimmerfest | G20: 25 | H20: abonado el 11/12/2025 por fede
A21: FILTRO M2 ABEL | B21: 40 | C21: FEDE | D21: SI | F21: Renovacion de dominio | G21: 22.17 | H21: pagado por nahue 24 jun 2025
A22: VRSF M2 ABEL | B22: 745 | C22: FEDE | D22: SI | F22: Google Workspace desde Julio 24 a Enero 26 | G22: 358.04 | H22: pagado por nahue
A23: SENSOR N20 YANI | B23: 13 | C23: FEDE | D23: SI | F23: Via Cargo Downpipe Raptor | G23: 10 | H23: pagado por nahue
A24: LLANTAS M2 ABEL | B24: 2200 | C24: FEDE | D24: SI | F24: PUBLICIDAD IG | G24: 51.73 | H24: pagado por nahue
A25: SENSORES HONDA X5 | B25: 13 | C25: FEDE | D25: SI
A26: AUTITO ESCALA M2 | B26: 100 | C26: FEDE | D26: SI
A27: ZAPATILLAS MILAGROS MOUSO | B27: 100 | C27: FEDE | D27: SI
A28: DIVERTER M2 ABEL | B28: 30 | C28: FEDE | D28: SI
A29: SIDEMARKERS M2 ABEL | B29: 10 | C29: FEDE | D29: SI
A30: IACV HONDA | B30: 20 | C30: FEDE | D30: SI
A31: COLITAS M2 ABEL | B31: 80 | C31: FEDE | D31: SI
A32: RIÑONES M2 ABEL | B32: 40 | C32: FEDE | D32: SI
A33: MODULOS HONDA X5 | B33: 40 | C33: NAHUE | D33: SI
A34: ALERON M2 ABEL | B34: 120 | C34: NAHUE | D34: SI
A35: ORDEN GRANDE M4 JUAN PAPA | B35: 2815 | C35: NAHUE | D35: SI
A36: CEPILLOS DETAIL NAHUE | B36: N/A | C36: N/A | D36: SI
A37: SWITCH MAZDA TANO | B37: N/A | C37: N/A | D37: SI
A38: INTERCOOLER VRSF OLMEDO | B38: 495 | C38: NAHUE | D38: SI
A39: REPUESTOS MARGOSIAN CAMARO | B39: 155 | C39: NAHUE | D39: SI
A40: ROPA JUAN PAPA | B40: 225 | C40: FEDE | D40: SI
A41: DISCOS TRASEROS M3 | B41: 630 | C41: FEDE | D41: SI
A42: PASTILLAS Y PARTS M3 TRAS | B42: 90 | C42: FEDE | D42: SI
A43: FILTRO KYN 335I | B43: 40 | C43: FEDE | D43: SI
A44: SENSOR LAND ROVER | B44: N/A | C44: FEDE | D44: SI
A45: BOMBA DORCH STG2 | B45: 120 | C45: NAHUE | D45: SI
A46: ESPEJOS M2 | B46: 120 | C46: NAHUE | D46: SI
A47: PARTES M4 PARTE 2 | B47: 360 | C47: NAHUE | D47: SI
A48: FLANGUE AGUA | B48: N/A | C48: FEDE | D48: SI
A49: TECHO MERCEDES | B49: 90 | C49: FEDE | D49: SI
A50: DUCHA | B50: 280 | C50: FEDE | D50: SI
A51: RADIADOR BMW | B51: 270 | C51: FEDE | D51: SI
A52: RIÑONES 335I F30 | B52: 40 | C52: FEDE | D52: SI
A53: GUARDAPLAST M4 PAPA | B53: 80 | C53: FEDE | D53: SI
A54: GUARDAPLAST HONDA | B54: 80 | C54: FEDE | D54: SI
A55: AMORTIGUADOR VOLVO | B55: 5 | C55: FEDE | D55: SI
A56: PLASTICO SAPITO | B56: 5 | C56: FEDE | D56: SI
A57: CHARGEPIPE N55 CASTELLVI | B57: 80 | C57: FEDE | D57: SI
A58: BUJES RS4 | B58: 160 | C58: FEDE | D58: SI
A59: ZAPAS AIRMAX | B59: 100 | C59: FEDE | D59: SI
A60: RADIADOR CSF 135I | B60: 180 | C60: FEDE | D60: SI
... A169: Luces interior Alan Olmedo | B169: 135 | C169: FEDE | D169: SI
A170: Adaptador y Modulo Leandro Ig | B170: $ - | C170: FEDE | D170: SI
A171: Compra Blowsion Alan Bruno | B171: 45 | C171: FEDE | D171: SI
A172: Lineas de freno Alan Olmedo | B172: 45 | C172: FEDE | D172: SI
A173: Fierros Factory Nerf | B173: 405 | C173: FEDE | D173: SI
A174: Charge pipe b58 Matias Virarelli | B174: 90 | C174: FEDE | D174: SI
A175: Inlet b58 Matias Virarelli | B175: 45 | C175: FEDE | D175: SI
A176: Embrague exedy | B176: 270 | C176: FEDE | D176: SI
A177: Cai Matias Virarelli | B177: 180 | C177: FEDE | D177: SI
A178: Modulo MB Coco Padilla | B178: 45 | C178: FEDE | D178: SI
A179: Tornillos ARP Nerf (embrague y tapa) | B179: 113 | C179: FEDE | D179: SI
A180: ECS Tapas de optica Leandro Ig | B180: 23 | C180: FEDE | D180: SI
A181: ECS Vanos Leandro Ig | B181: 23 | C181: FEDE | D181: SI
A182: Buje ECS Alan Olmedo | B182: 23 | C182: FEDE | D182: SI
... A215: Junta Speedfactory NERF | B215: 45 | C215: FEDE | D215: SI
A216: Pagos publicidad y gmail: https://trello.com/c/2kcmSxjE | B216: TBD | C216: NAHUE | D216: SI
A217: Pasaruedas 240i Luis | B217: 135 | C217: FEDE | D217: SI
A218: Spray Alan Olmedo | B218: 180 | C218: FEDE | D218: SI
A219: Difusor 240i Emiliano Righetti | B219: 135 | C219: FEDE | D219: SI
A220: Cachas carbono 240i Emiliano Righetti | B220: 90 | C220: FEDE | D220: SI
A221: Intake 240i Emiliano Righetti | B221: 180 | C221: FEDE | D221: SI
A222: Ecu Link Alan Olmedo M3 | B222: 270 | C222: FEDE | D222: SI
A223: Correa Gates Nerf | B223: $ - | C223: FEDE | D223: SI
A224: Ventilador Portables Nerf | B224: 45 | C224: FEDE | D224: SI
A225: Plaqueta bateria Abel | B225: 45 | C225: FEDE | D225: SI
A226: Embrague Luk Emiliano Righetti | B226: 360 | C226: FEDE | D226: SI
A227: Bomba interna Felix Scheuter | B227: 90 | C227: FEDE | D227: SI
A228: Tanque Moto Alan Klement | B228: 135 | C228: FEDE | D228: SI
A229: Colitas M perfomance Emiliano Righetti 240i | B229: 45 | C229: FEDE | D229: SI
A230: Patada Alan Klement | B230: $ - | C230: FEDE | D230: SI
A231: Protectores auditivos Franco Sciacarrillo | B231: 50 | C231: FEDE | D231: SI
A232: Parrilla MB Franco Sciacarrillo | B232: 45 | C232: FEDE | D232: SI
A233: Inyectores Felix | B233: 45 | C233: FEDE | D233: SI
A234: Tensores Daro Gaig | B234: 135 | C234: FEDE | D234: SI
A235: Espaciadores Daro Gaig | B235: 135 | C235: FEDE | D235: SI
A236: Regulador ventana Leandro Contigiani | B236: 45 | C236: FEDE | D236: SI
A237: Cinta bmw Leandro Contigiani | B237: 15 | C237: FEDE | D237: SI
A238: Sensor Thomas Shaw x1 | B238: 15 | C238: FEDE | D238: SI
A239: Reloj Aeromotive Nerf | B239: 15 | C239: FEDE | D239: SI
A240: Abel Termica | B240: 45 | C240: FEDE | D240: SI
A241: Iphone Karina Mora | B241: 150 | C241: FEDE | D241: SI
...
